{"1":[{"ref":"isaiah+14:23","label":"Isa 14:23"},{"ref":"isaiah+13:1","label":"Isa 13:1"},{"ref":"jeremiah+51:42","label":"Jer 51:42"},{"ref":"zechariah+9:14","label":"Zech 9:14"},{"ref":"isaiah+17:1","label":"Isa 17:1"},{"ref":"daniel+11:40","label":"Dan 11:40"},{"ref":"ezekiel+31:12","label":"Ezek 31:12"},{"ref":"job+37:9","label":"Job 37:9"}],"2":[{"ref":"jeremiah+49:34","label":"Jer 49:34"},{"ref":"isaiah+33:1","label":"Isa 33:1"},{"ref":"isaiah+24:16","label":"Isa 24:16"},{"ref":"psalms+60:3","label":"Ps 60:3"},{"ref":"daniel+5:28","label":"Dan 5:28"},{"ref":"revelation+13:10","label":"Rev 13:10"},{"ref":"psalms+12:5","label":"Ps 12:5"},{"ref":"1samuel+24:13","label":"1 Sam 24:13"}],"3":[{"ref":"isaiah+13:8","label":"Isa 13:8"},{"ref":"psalms+48:6","label":"Ps 48:6"},{"ref":"isaiah+26:17","label":"Isa 26:17"},{"ref":"1thessalonians+5:3","label":"1 Thess 5:3"},{"ref":"jeremiah+48:41","label":"Jer 48:41"},{"ref":"isaiah+16:11","label":"Isa 16:11"},{"ref":"jeremiah+50:43","label":"Jer 50:43"},{"ref":"habakkuk+3:16","label":"Hab 3:16"}],"4":[{"ref":"daniel+5:1","label":"Dan 5:1"},{"ref":"deuteronomy+28:67","label":"Deut 28:67"},{"ref":"esther+5:12","label":"Esth 5:12"},{"ref":"daniel+5:5","label":"Dan 5:5"},{"ref":"nahum+1:10","label":"Nah 1:10"},{"ref":"jeremiah+51:39","label":"Jer 51:39"},{"ref":"jeremiah+51:57","label":"Jer 51:57"},{"ref":"daniel+5:30","label":"Dan 5:30"}],"5":[{"ref":"jeremiah+51:11","label":"Jer 51:11"},{"ref":"jeremiah+51:39","label":"Jer 51:39"},{"ref":"jeremiah+51:57","label":"Jer 51:57"},{"ref":"1corinthians+15:32","label":"1 Cor 15:32"},{"ref":"isaiah+13:2","label":"Isa 13:2"}],"6":[{"ref":"ezekiel+3:17","label":"Ezek 3:17"},{"ref":"isaiah+62:6","label":"Isa 62:6"}],"7":[{"ref":"isaiah+21:9","label":"Isa 21:9"},{"ref":"hebrews+2:1","label":"Heb 2:1"},{"ref":"isaiah+37:24","label":"Isa 37:24"}],"8":[{"ref":"isaiah+56:10","label":"Isa 56:10"},{"ref":"isaiah+5:29","label":"Isa 5:29"},{"ref":"1peter+5:8","label":"1 Pet 5:8"},{"ref":"jeremiah+49:19","label":"Jer 49:19"},{"ref":"psalms+127:1","label":"Ps 127:1"},{"ref":"isaiah+62:6","label":"Isa 62:6"},{"ref":"jeremiah+50:44","label":"Jer 50:44"},{"ref":"jeremiah+4:7","label":"Jer 4:7"}],"9":[{"ref":"revelation+18:2","label":"Rev 18:2"},{"ref":"revelation+14:8","label":"Rev 14:8"},{"ref":"jeremiah+51:8","label":"Jer 51:8"},{"ref":"jeremiah+51:44","label":"Jer 51:44"},{"ref":"isaiah+13:19","label":"Isa 13:19"},{"ref":"jeremiah+50:38","label":"Jer 50:38"},{"ref":"isaiah+14:4","label":"Isa 14:4"},{"ref":"jeremiah+51:52","label":"Jer 51:52"}],"10":[{"ref":"jeremiah+51:33","label":"Jer 51:33"},{"ref":"micah+4:13","label":"Mic 4:13"},{"ref":"2kings+13:7","label":"2 Kgs 13:7"},{"ref":"matthew+3:12","label":"Matt 3:12"},{"ref":"1kings+22:14","label":"1 Kgs 22:14"},{"ref":"habakkuk+3:12","label":"Hab 3:12"}],"11":[{"ref":"genesis+25:14","label":"Gen 25:14"},{"ref":"amos+1:6","label":"Amos 1:6"},{"ref":"joel+3:19","label":"Joel 3:19"},{"ref":"genesis+32:3","label":"Gen 32:3"},{"ref":"psalms+137:7","label":"Ps 137:7"},{"ref":"deuteronomy+2:5","label":"Deut 2:5"},{"ref":"numbers+24:18","label":"Num 24:18"},{"ref":"isaiah+21:6","label":"Isa 21:6"}],"12":[{"ref":"isaiah+17:14","label":"Isa 17:14"},{"ref":"ezekiel+7:10","label":"Ezek 7:10"},{"ref":"ezekiel+7:12","label":"Ezek 7:12"},{"ref":"isaiah+55:7","label":"Isa 55:7"},{"ref":"jeremiah+50:27","label":"Jer 50:27"}],"13":[{"ref":"1chronicles+1:32","label":"1 Chr 1:32"},{"ref":"genesis+25:3","label":"Gen 25:3"},{"ref":"ezekiel+27:15","label":"Ezek 27:15"},{"ref":"isaiah+13:20","label":"Isa 13:20"},{"ref":"1chronicles+1:9","label":"1 Chr 1:9"},{"ref":"isaiah+13:1","label":"Isa 13:1"},{"ref":"1kings+10:15","label":"1 Kgs 10:15"},{"ref":"galatians+4:25","label":"Gal 4:25"}],"14":[{"ref":"job+6:19","label":"Job 6:19"},{"ref":"genesis+25:15","label":"Gen 25:15"},{"ref":"proverbs+25:21","label":"Prov 25:21"},{"ref":"romans+12:20","label":"Rom 12:20"},{"ref":"1peter+4:9","label":"1 Pet 4:9"},{"ref":"1chronicles+1:30","label":"1 Chr 1:30"}],"15":[{"ref":"isaiah+13:14","label":"Isa 13:14"}],"16":[{"ref":"isaiah+60:7","label":"Isa 60:7"},{"ref":"isaiah+16:14","label":"Isa 16:14"},{"ref":"songofsolomon+1:5","label":"Song 1:5"},{"ref":"psalms+120:5","label":"Ps 120:5"},{"ref":"ezekiel+27:21","label":"Ezek 27:21"},{"ref":"jeremiah+49:28","label":"Jer 49:28"},{"ref":"genesis+25:13","label":"Gen 25:13"},{"ref":"isaiah+42:11","label":"Isa 42:11"}],"17":[{"ref":"zechariah+1:6","label":"Zech 1:6"},{"ref":"numbers+23:19","label":"Num 23:19"},{"ref":"isaiah+1:20","label":"Isa 1:20"},{"ref":"matthew+24:35","label":"Matt 24:35"},{"ref":"jeremiah+44:29","label":"Jer 44:29"},{"ref":"psalms+107:39","label":"Ps 107:39"}]}