{"1":[{"t":"אֶפְרַ֔יִם","g":"Ephraim","s":"669","c":"noun","tr":"ʾep̄rayim"},{"t":"בֵּ֣ית","g":"the.house","s":"1004","c":"noun","tr":"bēyṯ"},{"t":"יִשְׂרָאֵ֑ל","g":"of.Israel","s":"3478","c":"noun","tr":"yiśrāʾēl"},{"t":"עֹ֥ד","g":"still","s":"5750","c":"adv","tr":"ʿōḏ"},{"t":"רָד֙","g":"it.has.roamed.freely","s":"7300","c":"verb","tr":"rāḏ"},{"t":"עִם","g":"with","s":"5973","c":"prep","tr":"ʿim-"},{"t":"אֵ֔ל","g":"God","s":"0410","c":"noun","tr":"ʾēl"},{"t":"קְדוֹשִׁ֖ים","g":"[the].holy.[one(s)]","s":"6918","c":"adj","tr":"qəḏôšiym"},{"t":"נֶאֱמָֽן","g":"[it.is].faithful","s":"539","c":"verb","tr":"neʾĕmān:"}],"2":[{"t":"אֶפְרַ֜יִם","g":"Ephraim","s":"669","c":"noun","tr":"ʾep̄rayim"},{"t":"רֹעֶ֥ה","g":"[is].feeding","s":"7462","c":"verb","tr":"rōʿeh"},{"t":"ר֨וּחַ֙","g":"wind","s":"7307","c":"noun","tr":"rûḥa"},{"t":"קָדִ֔ים","g":"an.east.wind","s":"6921","c":"noun","tr":"qāḏiym"},{"t":"כָּל","g":"all","s":"3605","c":"noun","tr":"kol-"},{"t":"כָּזָ֥ב","g":"falsehood","s":"3577","c":"noun","tr":"kāzāḇ"},{"t":"יַרְבֶּ֑ה","g":"he.increases","s":"7235","c":"verb","tr":"yarbeh"},{"t":"עִם","g":"with","s":"5973","c":"prep","tr":"ʿim-"},{"t":"אַשּׁ֣וּר","g":"Assyria","s":"804","c":"noun","tr":"ʾaššûr"},{"t":"יִכְרֹ֔תוּ","g":"they.are.making","s":"3772","c":"verb","tr":"yiḵrōṯû"},{"t":"יוּבָֽל","g":"it.is.carried","s":"2986","c":"verb","tr":"yûḇāl:"}],"3":[{"t":"עִם","g":"with","s":"5973","c":"prep","tr":"ʿim-"},{"t":"יְהוּדָ֑ה","g":"Judah","s":"3063","c":"noun","tr":"yəhûḏāh"},{"t":"עַֽל","g":"on","s":"5921","c":"prep","tr":"ʿal-"},{"t":"יַעֲקֹב֙","g":"Jacob","s":"3290","c":"noun","tr":"yaʿăqōḇ"},{"t":"יָשִׁ֥יב","g":"he.will.repay","s":"7725","c":"verb","tr":"yāšiyḇ"}],"4":[{"t":"עָקַ֣ב","g":"he.took.by.the.heel","s":"6117","c":"verb","tr":"ʿāqaḇ"},{"t":"אֶת","g":"(et)","s":"853","c":"om","tr":"ʾeṯ-"},{"t":"שָׂרָ֥ה","g":"he.struggled","s":"8280","c":"verb","tr":"śārāh"},{"t":"אֶת","g":"with","s":"854","c":"prep","tr":"ʾeṯ-"},{"t":"אֱלֹהִֽים","g":"God","s":"0430","c":"noun","tr":"ʾĕlōhiym:"}],"5":[{"t":"אֶל","g":"against","s":"0413","c":"prep","tr":"ʾel-"},{"t":"מַלְאָךְ֙","g":"an.angel","s":"4397","c":"noun","tr":"malʾāḵə"},{"t":"בָּכָ֖ה","g":"he.wept","s":"1058","c":"verb","tr":"bāḵāh"},{"t":"יְדַבֵּ֥ר","g":"he.spoke","s":"1696","c":"verb","tr":"yəḏabbēr"}],"6":[{"t":"אֱלֹהֵ֣י","g":"the.God","s":"0430","c":"noun","tr":"ʾĕlōhēy"},{"t":"יְהוָ֖ה","g":"Yahweh","s":"3068","c":"noun","tr":"yəhwāh"}],"7":[{"t":"תָשׁ֑וּב","g":"you.will.return","s":"7725","c":"verb","tr":"ṯāšûḇ"},{"t":"חֶ֤סֶד","g":"loyalty","s":"2617","c":"noun","tr":"ḥeseḏ"},{"t":"שְׁמֹ֔ר","g":"keep","s":"8104","c":"verb","tr":"šəmōr"},{"t":"אֶל","g":"to","s":"0413","c":"prep","tr":"ʾel-"},{"t":"תָּמִֽיד","g":"continually","s":"8548","c":"adv","tr":"tāmiyḏ:"}],"8":[{"t":"כְּנַ֗עַן","g":"a.merchant","s":"3667a","c":"noun","tr":"kənaʿan"},{"t":"מֹאזְנֵ֥י","g":"balances","s":"3976","c":"noun","tr":"mōʾzənēy"},{"t":"מִרְמָ֖ה","g":"of.deceit","s":"4820","c":"noun","tr":"mirmāh"},{"t":"אָהֵֽב","g":"he.loves","s":"0157","c":"verb","tr":"ʾāhēḇ:"}],"9":[{"t":"אֶפְרַ֔יִם","g":"Ephraim","s":"669","c":"noun","tr":"ʾep̄rayim"},{"t":"אַ֣ךְ","g":"surely","s":"389","c":"adv","tr":"ʾaḵ"},{"t":"עָשַׁ֔רְתִּי","g":"I.have.become.rich","s":"6238","c":"verb","tr":"ʿāšarətî"},{"t":"מָצָ֥אתִי","g":"I.have.found","s":"4672","c":"verb","tr":"māṣāʾṯî"},{"t":"א֖וֹן","g":"wealth","s":"0202","c":"noun","tr":"ʾôn"},{"t":"כָּל","g":"all","s":"3605","c":"noun","tr":"kol-"},{"t":"לֹ֥א","g":"not","s":"3808","c":"adv","tr":"lōʾ"},{"t":"יִמְצְאוּ","g":"people.will.find","s":"4672","c":"verb","tr":"yimṣəʾû-"},{"t":"עָוֺ֥ן","g":"iniquity","s":"5771","c":"noun","tr":"ʿāwōn"},{"t":"אֲשֶׁר","g":"which","s":"834","c":"rel","tr":"ʾăšer-"},{"t":"חֵֽטְא","g":"[is].sin","s":"2399","c":"noun","tr":"ḥēṭəʾ:"}],"10":[{"t":"יְהוָ֥ה","g":"[have.been].Yahweh","s":"3068","c":"noun","tr":"yəhwāh"},{"t":"מִצְרָ֑יִם","g":"of.Egypt","s":"4714","c":"noun","tr":"miṣrāyim"},{"t":"עֹ֛ד","g":"again","s":"5750","c":"adv","tr":"ʿōḏ"},{"t":"מוֹעֵֽד","g":"of.an.appointed.feast","s":"4150","c":"noun","tr":"môʿēḏ:"}],"11":[{"t":"עַל","g":"to","s":"5921","c":"prep","tr":"ʿal-"},{"t":"חָז֣וֹן","g":"vision[s]","s":"2377","c":"noun","tr":"ḥāzôn"},{"t":"הִרְבֵּ֑יתִי","g":"I.multiplied","s":"7235","c":"verb","tr":"hirbēyṯî"},{"t":"אֲדַמֶּֽה","g":"I.gave.parables","s":"1819","c":"verb","tr":"ʾăḏammeh:"}],"12":[{"t":"אִם","g":"(if)?","s":"518","c":"cj","tr":"ʾim-"},{"t":"גִּלְעָ֥ד","g":"[is].Gilead","s":"1568","c":"noun","tr":"gilʿāḏ"},{"t":"אָ֨וֶן֙","g":"wickedness","s":"0205","c":"noun","tr":"ʾāwen"},{"t":"אַךְ","g":"surely","s":"389","c":"adv","tr":"ʾaḵ-"},{"t":"שָׁ֣וְא","g":"worthlessness","s":"7723","c":"noun","tr":"šāwəʾ"},{"t":"הָי֔וּ","g":"they.are","s":"1961","c":"verb","tr":"hāyû"},{"t":"שְׁוָרִ֣ים","g":"bulls","s":"7794","c":"noun","tr":"šəwāriym"},{"t":"זִבֵּ֑חוּ","g":"they.have.sacrificed","s":"2076","c":"verb","tr":"zibbēḥû"},{"t":"גַּ֤ם","g":"also","s":"1571","c":"cj","tr":"gam"},{"t":"עַ֖ל","g":"on","s":"5921","c":"prep","tr":"ʿal"},{"t":"תַּלְמֵ֥י","g":"[the].furrows","s":"8525","c":"noun","tr":"talmēy"},{"t":"שָׂדָֽי","g":"of.a.field","s":"7704a","c":"noun","tr":"śāḏāy:"}],"13":[{"t":"יַעֲקֹ֖ב","g":"Jacob","s":"3290","c":"noun","tr":"yaʿăqōḇ"},{"t":"שְׂדֵ֣ה","g":"the.region","s":"7704","c":"noun","tr":"śəḏēh"},{"t":"אֲרָ֑ם","g":"of.Aram","s":"758","c":"noun","tr":"ʾărām"},{"t":"יִשְׂרָאֵל֙","g":"Israel","s":"3478","c":"noun","tr":"yiśrāʾēl"},{"t":"שָׁמָֽר","g":"he.kept.[flocks]","s":"8104","c":"verb","tr":"šāmār:"}],"14":[{"t":"הֶעֱלָ֧ה","g":"he.brought.up","s":"5927","c":"verb","tr":"heʿĕlāh"},{"t":"יְהוָ֛ה","g":"Yahweh","s":"3068","c":"noun","tr":"yəhwāh"},{"t":"אֶת","g":"(et)","s":"853","c":"om","tr":"ʾeṯ-"},{"t":"יִשְׂרָאֵ֖ל","g":"Israel","s":"3478","c":"noun","tr":"yiśrāʾēl"},{"t":"נִשְׁמָֽר","g":"he.was.kept","s":"8104","c":"verb","tr":"nišmār:"}],"15":[{"t":"הִכְעִ֥יס","g":"he.has.provoked.to.anger","s":"3707","c":"verb","tr":"hiḵʿiys"},{"t":"אֶפְרַ֖יִם","g":"Ephraim","s":"669","c":"noun","tr":"ʾep̄rayim"},{"t":"תַּמְרוּרִ֑ים","g":"bitterness(es)","s":"8563","c":"noun","tr":"tamrûriym"},{"t":"יִטּ֔וֹשׁ","g":"he.will.leave","s":"5203","c":"verb","tr":"yiṭṭôš"},{"t":"יָשִׁ֥יב","g":"he.will.repay","s":"7725","c":"verb","tr":"yāšiyḇ"}]}