{"1":[{"t":"אֶל","g":"to","s":"0413","c":"prep","tr":"ʾel-"},{"t":"שָׁא֔וּל","g":"Saul","s":"7586","c":"noun","tr":"šāʾûl"},{"t":"יְה֣וֹנָתָ֔ן","g":"of.Jonathan","s":"3083","c":"noun","tr":"yəhônāṯān"},{"t":"נִקְשְׁרָ֖ה","g":"it.was.bound","s":"7194","c":"verb","tr":"niqšərāh"},{"t":"דָּוִ֑ד","g":"of.David","s":"1732","c":"noun","tr":"dāwiḏ"},{"t":"יְהוֹנָתָ֖ן","g":"Jonathan","s":"3083","c":"noun","tr":"yəhônāṯān"}],"2":[{"t":"שָׁא֖וּל","g":"Saul","s":"7586","c":"noun","tr":"šāʾûl"},{"t":"בֵּ֥ית","g":"the.house","s":"1004","c":"noun","tr":"bēyṯ"}],"3":[{"t":"יְהוֹנָתָ֛ן","g":"Jonathan","s":"3083","c":"noun","tr":"yəhônāṯān"},{"t":"בְּרִ֑ית","g":"a.covenant","s":"1285","c":"noun","tr":"bəriyṯ"}],"4":[{"t":"יְהוֹנָתָ֗ן","g":"Jonathan","s":"3083","c":"noun","tr":"yəhônāṯān"},{"t":"אֶֽת","g":"(et)","s":"853","c":"om","tr":"ʾeṯ-"},{"t":"אֲשֶׁ֣ר","g":"which","s":"834","c":"rel","tr":"ʾăšer"}],"5":[{"t":"דָוִ֜ד","g":"David","s":"1732","c":"noun","tr":"ḏāwiḏ"},{"t":"אֲשֶׁ֨ר","g":"where","s":"834","c":"rel","tr":"ʾăšer"},{"t":"שָׁאוּל֙","g":"Saul","s":"7586","c":"noun","tr":"šāʾûl"},{"t":"יַשְׂכִּ֔יל","g":"he.prospered","s":"7919","c":"verb","tr":"yaśkiyl"},{"t":"שָׁא֔וּל","g":"Saul","s":"7586","c":"noun","tr":"šāʾûl"},{"t":"עַ֖ל","g":"over","s":"5921","c":"prep","tr":"ʿal"},{"t":"אַנְשֵׁ֣י","g":"the.men","s":"0376","c":"noun","tr":"ʾanšēy"},{"t":"כָל","g":"of.all","s":"3605","c":"noun","tr":"ḵol-"},{"t":"עַבְדֵ֥י","g":"of.the.servants","s":"5650","c":"noun","tr":"ʿaḇḏēy"},{"t":"שָׁאֽוּל","g":"of.Saul","s":"7586","c":"noun","tr":"šāʾûl:"}],"6":[{"t":"דָּוִד֙","g":"David","s":"1732","c":"noun","tr":"dāwiḏ"},{"t":"אֶת","g":"(et)","s":"853","c":"om","tr":"ʾeṯ-"},{"t":"עָרֵ֤י","g":"the.cities","s":"5892","c":"noun","tr":"ʿārēy"},{"t":"יִשְׂרָאֵל֙","g":"of.Israel","s":"3478","c":"noun","tr":"yiśrāʾēl"},{"t":"שָׁא֣וּל","g":"Saul","s":"7586","c":"noun","tr":"šāʾûl"}],"7":[{"t":"הִכָּ֤ה","g":"he.has.struck.down","s":"5221","c":"verb","tr":"hikkāh"},{"t":"שָׁאוּל֙","g":"Saul","s":"7586","c":"noun","tr":"šāʾûl"}],"8":[{"t":"מְאֹ֗ד","g":"exceedingly","s":"3966","c":"adv","tr":"məʾōḏ"},{"t":"נָתְנ֤וּ","g":"they.have.ascribed","s":"5414","c":"verb","tr":"nāṯənû"},{"t":"רְבָב֔וֹת","g":"ten.thousands","s":"7233","c":"num","tr":"rəḇāḇôṯ"},{"t":"נָתְנ֖וּ","g":"they.have.ascribed","s":"5414","c":"verb","tr":"nāṯənû"},{"t":"אַ֥ךְ","g":"only","s":"389","c":"adv","tr":"ʾaḵ"}],"9":[{"t":"שָׁא֖וּל","g":"Saul","s":"7586","c":"noun","tr":"šāʾûl"},{"t":"עוֹיֵ֣ן","g":"looking.suspiciously.at","s":"5770a","c":"verb","tr":"**ʿôyēn"},{"t":"אֶת","g":"(et)","s":"853","c":"om","tr":"ʾeṯ-"},{"t":"דָּוִ֑ד","g":"David","s":"1732","c":"noun","tr":"dāwiḏ"}],"10":[{"t":"רוּחַ֩","g":"a.spirit","s":"7307","c":"noun","tr":"rûḥa"},{"t":"אֱלֹהִ֨ים","g":"of.God","s":"0430","c":"noun","tr":"ʾĕlōhiym"},{"t":"רָעָ֤ה","g":"evil","s":"7451","c":"adj","tr":"rāʿāh"},{"t":"אֶל","g":"to","s":"0413","c":"prep","tr":"ʾel-"},{"t":"שָׁאוּל֙","g":"Saul","s":"7586","c":"noun","tr":"šāʾûl"},{"t":"מְנַגֵּ֥ן","g":"[was].playing","s":"5059","c":"verb","tr":"mənaggēn"},{"t":"שָׁאֽוּל","g":"of.Saul","s":"7586","c":"noun","tr":"šāʾûl:"}],"11":[{"t":"שָׁאוּל֙","g":"Saul","s":"7586","c":"noun","tr":"šāʾûl"},{"t":"אֶֽת","g":"(et)","s":"853","c":"om","tr":"ʾeṯ-"},{"t":"אַכֶּ֥ה","g":"I.will.strike","s":"5221","c":"verb","tr":"ʾakkeh"},{"t":"דָּוִ֛ד","g":"David","s":"1732","c":"noun","tr":"dāwiḏ"},{"t":"פַּעֲמָֽיִם","g":"two.times","s":"6471","c":"noun","tr":"paʿămāyim:"}],"12":[{"t":"שָׁא֖וּל","g":"Saul","s":"7586","c":"noun","tr":"šāʾûl"},{"t":"דָוִ֑ד","g":"David","s":"1732","c":"noun","tr":"ḏāwiḏ"},{"t":"כִּֽי","g":"(dm)","s":"3588","c":"cj","tr":"kiy-"},{"t":"הָיָ֤ה","g":"he.was","s":"1961","c":"verb","tr":"hāyāh"},{"t":"יְהוָה֙","g":"Yahweh","s":"3068","c":"noun","tr":"yhwh"},{"t":"שָׁא֖וּל","g":"Saul","s":"7586","c":"noun","tr":"šāʾûl"},{"t":"סָֽר","g":"he.had.turned.aside","s":"5493","c":"verb","tr":"sār:"}],"13":[{"t":"שָׁאוּל֙","g":"Saul","s":"7586","c":"noun","tr":"šāʾûl"},{"t":"שַׂר","g":"a.commander","s":"8269","c":"noun","tr":"śar-"},{"t":"אָ֑לֶף","g":"of.a.thousand","s":"0505","c":"num","tr":"ʾālep̄"}],"14":[{"t":"דָוִ֛ד","g":"David","s":"1732","c":"noun","tr":"ḏāwiḏ"},{"t":"מַשְׂכִּ֑יל","g":"[being].successful","s":"7919","c":"verb","tr":"maśkiyl"}],"15":[{"t":"שָׁא֔וּל","g":"Saul","s":"7586","c":"noun","tr":"šāʾûl"},{"t":"אֲשֶׁר","g":"(cmp)","s":"834","c":"rel","tr":"ʾăšer-"},{"t":"ה֖וּא","g":"he","s":"1931","c":"pron","tr":"hûʾ"},{"t":"מַשְׂכִּ֣יל","g":"[was.being].successful","s":"7919","c":"verb","tr":"maśkiyl"},{"t":"מְאֹ֑ד","g":"exceedingly","s":"3966","c":"adv","tr":"məʾōḏ"}],"16":[{"t":"יִשְׂרָאֵל֙","g":"Israel","s":"3478","c":"noun","tr":"yiśrāʾēl"},{"t":"אֹהֵ֖ב","g":"[was].loving","s":"0157","c":"verb","tr":"ʾōhēḇ"},{"t":"אֶת","g":"(et)","s":"853","c":"om","tr":"ʾeṯ-"},{"t":"דָּוִ֑ד","g":"David","s":"1732","c":"noun","tr":"dāwiḏ"},{"t":"כִּֽי","g":"(dm)","s":"3588","c":"cj","tr":"kiy-"},{"t":"ה֛וּא","g":"he","s":"1931","c":"pron","tr":"hûʾ"},{"t":"יוֹצֵ֥א","g":"[was].going.out","s":"3318","c":"verb","tr":"yôṣēʾ"}],"17":[{"t":"שָׁא֜וּל","g":"Saul","s":"7586","c":"noun","tr":"šāʾûl"},{"t":"אֶל","g":"to","s":"0413","c":"prep","tr":"ʾel-"},{"t":"דָּוִ֗ד","g":"David","s":"1732","c":"noun","tr":"dāwiḏ"},{"t":"הִנֵּה֩","g":"here!","s":"2009","c":"ij","tr":"hinnēh"},{"t":"מֵרַב֙","g":"Merab","s":"4764","c":"noun","tr":"mēraḇ"},{"t":"אֶתֶּן","g":"I.will.give","s":"5414","c":"verb","tr":"ʾetten-"},{"t":"אַ֚ךְ","g":"only","s":"389","c":"adv","tr":"ʾaḵ"},{"t":"הֱיֵה","g":"become","s":"1961","c":"verb","tr":"hĕyēh-"},{"t":"חַ֔יִל","g":"of.strength","s":"2428","c":"noun","tr":"ḥayil"},{"t":"מִלְחֲמ֣וֹת","g":"the.battles","s":"4421","c":"noun","tr":"milḥămôṯ"},{"t":"יְהוָ֑ה","g":"of.Yahweh","s":"3068","c":"noun","tr":"yəhwāh"},{"t":"אָמַ֗ר","g":"he.said","s":"559","c":"verb","tr":"ʾāmar"},{"t":"אַל","g":"not","s":"408","c":"adv","tr":"ʾal-"},{"t":"תְּהִ֤י","g":"let.it.be","s":"1961","c":"verb","tr":"təhiy"},{"t":"יַד","g":"the.hand","s":"3027","c":"noun","tr":"yaḏ-"},{"t":"פְּלִשְׁתִּֽים","g":"of.[the].Philistines","s":"6430","c":"noun","tr":"pəlištiym:"}],"18":[{"t":"דָּוִ֜ד","g":"David","s":"1732","c":"noun","tr":"dāwiḏ"},{"t":"אֶל","g":"to","s":"0413","c":"prep","tr":"ʾel-"},{"t":"שָׁא֗וּל","g":"Saul","s":"7586","c":"noun","tr":"šāʾûl"},{"t":"מִ֤י","g":"who?","s":"4310","c":"pron","tr":"miy"},{"t":"אָֽנֹכִי֙","g":"[am].I","s":"595","c":"pron","tr":"ʾānōḵî"},{"t":"מִשְׁפַּ֥חַת","g":"the.clan","s":"4940","c":"noun","tr":"mišpaḥaṯ"},{"t":"כִּֽי","g":"(cmp)","s":"3588","c":"cj","tr":"kiy-"},{"t":"אֶהְיֶ֥ה","g":"I.will.be","s":"1961","c":"verb","tr":"ʾehyeh"},{"t":"חָתָ֖ן","g":"a.son-in-law","s":"2860","c":"noun","tr":"ḥāṯān"}],"19":[{"t":"תֵּ֛ת","g":"gave","s":"5414","c":"verb","tr":"tēṯ"},{"t":"אֶת","g":"(et)","s":"853","c":"om","tr":"ʾeṯ-"},{"t":"מֵרַ֥ב","g":"Merab","s":"4764","c":"noun","tr":"mēraḇ"},{"t":"בַּת","g":"the.daughter","s":"1323","c":"noun","tr":"baṯ-"},{"t":"שָׁא֖וּל","g":"of.Saul","s":"7586","c":"noun","tr":"šāʾûl"},{"t":"נִתְּנָ֛ה","g":"she.was.given","s":"5414","c":"verb","tr":"nittənāh"}],"20":[{"t":"מִיכַ֥ל","g":"Michal","s":"4324","c":"noun","tr":"mîḵal"},{"t":"בַּת","g":"the.daughter","s":"1323","c":"noun","tr":"baṯ-"},{"t":"שָׁא֖וּל","g":"of.Saul","s":"7586","c":"noun","tr":"šāʾûl"},{"t":"אֶת","g":"(et)","s":"853","c":"om","tr":"ʾeṯ-"},{"t":"דָּוִ֑ד","g":"David","s":"1732","c":"noun","tr":"dāwiḏ"}],"21":[{"t":"שָׁא֜וּל","g":"Saul","s":"7586","c":"noun","tr":"šāʾûl"},{"t":"יַד","g":"the.hand","s":"3027","c":"noun","tr":"yaḏ-"},{"t":"פְּלִשְׁתִּ֑ים","g":"of.[the].Philistines","s":"6430","c":"noun","tr":"pəlištiym"},{"t":"שָׁאוּל֙","g":"Saul","s":"7586","c":"noun","tr":"šāʾûl"},{"t":"אֶל","g":"to","s":"0413","c":"prep","tr":"ʾel-"},{"t":"דָּוִ֔ד","g":"David","s":"1732","c":"noun","tr":"dāwiḏ"},{"t":"תִּתְחַתֵּ֥ן","g":"you.will.be.a.son-in-law","s":"2859","c":"verb","tr":"tiṯḥattēn"}],"22":[{"t":"שָׁא֜וּל","g":"Saul","s":"7586","c":"noun","tr":"šāʾûl"},{"t":"אֶת","g":"(et)","s":"853","c":"om","tr":"ʾeṯ-"},{"t":"דַּבְּר֨וּ","g":"speak","s":"1696","c":"verb","tr":"dabbərû"},{"t":"אֶל","g":"to","s":"0413","c":"prep","tr":"ʾel-"},{"t":"דָּוִ֤ד","g":"David","s":"1732","c":"noun","tr":"dāwiḏ"},{"t":"הִנֵּ֨ה","g":"here!","s":"2009","c":"ij","tr":"hinnēh"},{"t":"חָפֵ֤ץ","g":"he.delights","s":"2654","c":"verb","tr":"ḥāp̄ēṣ"},{"t":"הִתְחַתֵּ֥ן","g":"be.son-in-law","s":"2859","c":"verb","tr":"hiṯḥattēn"}],"23":[{"t":"עַבְדֵ֤י","g":"the.servants","s":"5650","c":"noun","tr":"ʿaḇḏēy"},{"t":"שָׁאוּל֙","g":"of.Saul","s":"7586","c":"noun","tr":"šāʾûl"},{"t":"דָוִ֔ד","g":"of.David","s":"1732","c":"noun","tr":"ḏāwiḏ"},{"t":"אֶת","g":"(et)","s":"853","c":"om","tr":"ʾeṯ-"},{"t":"דָּוִ֗ד","g":"David","s":"1732","c":"noun","tr":"dāwiḏ"},{"t":"הִתְחַתֵּ֣ן","g":"[is].to.be.son-in-law","s":"2859","c":"verb","tr":"hiṯḥattēn"},{"t":"אִֽישׁ","g":"[am].a.man","s":"0376","c":"noun","tr":"ʾiyš-"},{"t":"רָ֥שׁ","g":"poor","s":"7326","c":"verb","tr":"rāš"}],"24":[{"t":"עַבְדֵ֥י","g":"the.servants","s":"5650","c":"noun","tr":"ʿaḇḏēy"},{"t":"שָׁא֛וּל","g":"of.Saul","s":"7586","c":"noun","tr":"šāʾûl"},{"t":"דִּבֶּ֥ר","g":"he.spoke","s":"1696","c":"verb","tr":"dibber"},{"t":"דָּוִֽד","g":"David","s":"1732","c":"noun","tr":"dāwiḏ:"}],"25":[{"t":"שָׁא֜וּל","g":"Saul","s":"7586","c":"noun","tr":"šāʾûl"},{"t":"כֹּֽה","g":"thus","s":"3541","c":"adv","tr":"kōh-"},{"t":"תֹאמְר֣וּ","g":"you.will.say","s":"559","c":"verb","tr":"ṯōʾmərû"},{"t":"אֵֽין","g":"there.[is].not","s":"369","c":"adv","tr":"ʾēyn-"},{"t":"חֵ֤פֶץ","g":"delight","s":"2656","c":"noun","tr":"ḥēp̄eṣ"},{"t":"כִּ֗י","g":"(dm)","s":"3588","c":"cj","tr":"kiy"},{"t":"עָרְל֣וֹת","g":"foreskins","s":"6190","c":"noun","tr":"ʿārəlôṯ"},{"t":"פְּלִשְׁתִּ֔ים","g":"of.Philistines","s":"6430","c":"noun","tr":"pəlištiym"},{"t":"חָשַׁ֔ב","g":"he.planned","s":"2803","c":"verb","tr":"ḥāšaḇ"},{"t":"אֶת","g":"(et)","s":"853","c":"om","tr":"ʾeṯ-"},{"t":"דָּוִ֖ד","g":"David","s":"1732","c":"noun","tr":"dāwiḏ"},{"t":"פְּלִשְׁתִּֽים","g":"of.[the].Philistines","s":"6430","c":"noun","tr":"pəlištiym:"}],"26":[{"t":"אֶת","g":"(et)","s":"853","c":"om","tr":"ʾeṯ-"},{"t":"דָוִ֔ד","g":"of.David","s":"1732","c":"noun","tr":"ḏāwiḏ"},{"t":"מָלְא֖וּ","g":"they.were.completed","s":"4390","c":"verb","tr":"mālʾû"}],"27":[{"t":"דָּוִ֜ד","g":"David","s":"1732","c":"noun","tr":"dāwiḏ"},{"t":"ה֣וּא","g":"he","s":"1931","c":"pron","tr":"hûʾ"},{"t":"מָאתַ֣יִם","g":"two.hundred","s":"3967","c":"num","tr":"māʾṯayim"},{"t":"אִישׁ֒","g":"man","s":"0376","c":"noun","tr":"ʾîš"},{"t":"דָוִד֙","g":"David","s":"1732","c":"noun","tr":"ḏāwiḏ"},{"t":"אֶת","g":"(et)","s":"853","c":"om","tr":"ʾeṯ-"},{"t":"שָׁא֛וּל","g":"Saul","s":"7586","c":"noun","tr":"šāʾûl"},{"t":"אֶת","g":"(et)","s":"853","c":"om","tr":"ʾeṯ-"},{"t":"מִיכַ֥ל","g":"Michal","s":"4324","c":"noun","tr":"mîḵal"}],"28":[{"t":"שָׁאוּל֙","g":"Saul","s":"7586","c":"noun","tr":"šāʾûl"},{"t":"כִּ֥י","g":"(dm).that","s":"3588","c":"cj","tr":"kiy"},{"t":"יְהוָ֖ה","g":"Yahweh","s":"3068","c":"noun","tr":"yəhwāh"},{"t":"עִם","g":"[was].with","s":"5973","c":"prep","tr":"ʿim-"},{"t":"דָּוִ֑ד","g":"David","s":"1732","c":"noun","tr":"dāwiḏ"},{"t":"בַּת","g":"the.daughter","s":"1323","c":"noun","tr":"baṯ-"},{"t":"שָׁא֖וּל","g":"of.Saul","s":"7586","c":"noun","tr":"šāʾûl"}],"29":[{"t":"שָׁא֗וּל","g":"Saul","s":"7586","c":"noun","tr":"šāʾûl"},{"t":"דָוִ֖ד","g":"David","s":"1732","c":"noun","tr":"ḏāwiḏ"},{"t":"ע֑וֹד","g":"again","s":"5750","c":"adv","tr":"ʿôḏ"},{"t":"שָׁא֛וּל","g":"Saul","s":"7586","c":"noun","tr":"šāʾûl"},{"t":"אֹיֵ֥ב","g":"an.enemy","s":"0341","c":"noun","tr":"ʾōyēḇ"},{"t":"אֶת","g":"(et)","s":"853","c":"om","tr":"ʾeṯ-"},{"t":"דָּוִ֖ד","g":"David","s":"1732","c":"noun","tr":"dāwiḏ"},{"t":"כָּל","g":"all","s":"3605","c":"noun","tr":"kol-"}],"30":[{"t":"שָׂרֵ֣י","g":"the.commanders","s":"8269","c":"noun","tr":"śārēy"},{"t":"פְלִשְׁתִּ֑ים","g":"of.[the].Philistines","s":"6430","c":"noun","tr":"p̄əlištiym"},{"t":"שָׂכַ֤ל","g":"he.was.successful","s":"7919","c":"verb","tr":"śāḵal"},{"t":"דָּוִד֙","g":"David","s":"1732","c":"noun","tr":"dāwiḏ"},{"t":"עַבְדֵ֣י","g":"the.servants","s":"5650","c":"noun","tr":"ʿaḇḏēy"},{"t":"שָׁא֔וּל","g":"of.Saul","s":"7586","c":"noun","tr":"šāʾûl"},{"t":"מְאֹֽד","g":"exceedingly","s":"3966","c":"adv","tr":"məʾōḏ:"}]}