{"1":[{"t":"δὲ","g":"then","s":"1161","c":"conj"},{"t":"Ἐγένετο","g":"It came to pass","s":"1096","c":"verb"},{"t":"ἐν","g":"on","s":"1722","c":"prep"},{"t":"σαββάτῳ","g":"a Sabbath","s":"4521","c":"noun"},{"t":"διαπορεύεσθαι","g":"is passing along","s":"1279","c":"verb"},{"t":"αὐτὸν","g":"He","s":"846","c":"pron"},{"t":"διὰ","g":"through","s":"1223","c":"prep"},{"t":"σπορίμων","g":"grainfields","s":"4702","c":"adj"},{"t":"καὶ","g":"and","s":"2532","c":"conj"},{"t":"ἔτιλλον","g":"were plucking","s":"5089","c":"verb"},{"t":"καὶ","g":"and","s":"2532","c":"conj"},{"t":"ἤσθιον","g":"were eating","s":"2068","c":"verb"},{"t":"μαθηταὶ","g":"disciples","s":"3101","c":"noun"},{"t":"αὐτοῦ","g":"of Him","s":"846","c":"pron"},{"t":"στάχυας","g":"heads of grain","s":"4719","c":"noun"},{"t":"ψώχοντες","g":"rubbing [them]","s":"5597","c":"verb"},{"t":"χερσίν","g":"hands","s":"5495","c":"noun"}],"2":[{"t":"δὲ","g":"however","s":"1161","c":"conj"},{"t":"τινὲς","g":"Some","s":"5100","c":"pron"},{"t":"Φαρισαίων","g":"Pharisees","s":"5330","c":"noun"},{"t":"εἶπαν","g":"said","s":"3004","c":"verb"},{"t":"Τί","g":"Why","s":"5101","c":"pron"},{"t":"ποιεῖτε","g":"do you","s":"4160","c":"verb"},{"t":"ὃ","g":"that which","s":"3739","c":"pron"},{"t":"οὐκ","g":"not","s":"3756","c":"adv"},{"t":"ἔξεστιν","g":"it is lawful","s":"1832","c":"verb"},{"t":"σάββασιν","g":"Sabbaths","s":"4521","c":"noun"}],"3":[{"t":"καὶ","g":"And","s":"2532","c":"conj"},{"t":"ἀποκριθεὶς","g":"answering","s":"611","c":"verb"},{"t":"πρὸς","g":"to","s":"4314","c":"prep"},{"t":"αὐτοὺς","g":"them","s":"846","c":"pron"},{"t":"εἶπεν","g":"said","s":"3004","c":"verb"},{"t":"Ἰησοῦς","g":"Jesus","s":"2424","c":"noun"},{"t":"Οὐδὲ","g":"Not even","s":"3761","c":"adv"},{"t":"ἀνέγνωτε","g":"have you read","s":"314","c":"verb"},{"t":"τοῦτο","g":"this","s":"3778","c":"pron"},{"t":"ὃ","g":"that which","s":"3739","c":"pron"},{"t":"ἐποίησεν","g":"did","s":"4160","c":"verb"},{"t":"Δαυεὶδ","g":"David","s":"1138","c":"noun"},{"t":"ὁπότε","g":"when","s":"3698","c":"conj"},{"t":"ἐπείνασεν","g":"was hungry","s":"3983","c":"verb"},{"t":"αὐτὸς","g":"he himself","s":"846","c":"pron"},{"t":"καὶ","g":"and","s":"2532","c":"conj"},{"t":"μετ’","g":"with","s":"3326","c":"prep"},{"t":"αὐτοῦ","g":"him","s":"846","c":"pron"},{"t":"ὄντες","g":"were","s":"1510","c":"verb"},{"t":"ὡς","g":"how","s":"5613","c":"conj"},{"t":"εἰσῆλθεν","g":"he entered","s":"1525","c":"verb"},{"t":"εἰς","g":"into","s":"1519","c":"prep"},{"t":"οἶκον","g":"house","s":"3624","c":"noun"},{"t":"Θεοῦ","g":"of God","s":"2316","c":"noun"},{"t":"καὶ","g":"and","s":"2532","c":"conj"},{"t":"ἄρτους","g":"loaves","s":"740","c":"noun"},{"t":"προθέσεως","g":"presentation","s":"4286","c":"noun"},{"t":"λαβὼν","g":"having taken","s":"2983","c":"verb"},{"t":"ἔφαγεν","g":"ate","s":"5315","c":"verb"},{"t":"καὶ","g":"and","s":"2532","c":"conj"},{"t":"ἔδωκεν","g":"gave","s":"1325","c":"verb"},{"t":"μετ’","g":"with","s":"3326","c":"prep"},{"t":"αὐτοῦ","g":"him","s":"846","c":"pron"},{"t":"οὓς","g":"which","s":"3739","c":"pron"},{"t":"φαγεῖν","g":"to eat","s":"5315","c":"verb"},{"t":"οὐκ","g":"not","s":"3756","c":"adv"},{"t":"ἔξεστιν","g":"it is lawful","s":"1832","c":"verb"},{"t":"εἰ","g":"if","s":"1487","c":"conj"},{"t":"μὴ","g":"not","s":"3361","c":"adv"},{"t":"μόνους","g":"only","s":"3441","c":"adj"},{"t":"ἱερεῖς","g":"priests","s":"2409","c":"noun"}],"5":[{"t":"καὶ","g":"And","s":"2532","c":"conj"},{"t":"ἔλεγεν","g":"He was saying","s":"3004","c":"verb"},{"t":"αὐτοῖς","g":"to them","s":"846","c":"pron"},{"t":"ἐστιν","g":"is","s":"1510","c":"verb"},{"t":"Κύριός","g":"Lord","s":"2962","c":"noun"},{"t":"σαββάτου","g":"Sabbath","s":"4521","c":"noun"},{"t":"Υἱὸς","g":"Son","s":"5207","c":"noun"},{"t":"ἀνθρώπου","g":"of Man","s":"444","c":"noun"}],"6":[{"t":"δὲ","g":"then","s":"1161","c":"conj"},{"t":"Ἐγένετο","g":"It came to pass","s":"1096","c":"verb"},{"t":"ἐν","g":"on","s":"1722","c":"prep"},{"t":"ἑτέρῳ","g":"another","s":"2087","c":"adj"},{"t":"σαββάτῳ","g":"Sabbath","s":"4521","c":"noun"},{"t":"εἰσελθεῖν","g":"entered","s":"1525","c":"verb"},{"t":"αὐτὸν","g":"He","s":"846","c":"pron"},{"t":"εἰς","g":"into","s":"1519","c":"prep"},{"t":"συναγωγὴν","g":"synagogue","s":"4864","c":"noun"},{"t":"καὶ","g":"and","s":"2532","c":"conj"},{"t":"διδάσκειν","g":"taught","s":"1321","c":"verb"},{"t":"καὶ","g":"and","s":"2532","c":"conj"},{"t":"ἦν","g":"there was","s":"1510","c":"verb"},{"t":"ἄνθρωπος","g":"a man","s":"444","c":"noun"},{"t":"ἐκεῖ","g":"there","s":"1563","c":"adv"},{"t":"καὶ","g":"and","s":"2532","c":"conj"},{"t":"χεὶρ","g":"hand","s":"5495","c":"noun"},{"t":"αὐτοῦ","g":"of him","s":"846","c":"pron"},{"t":"δεξιὰ","g":"right","s":"1188","c":"adj"},{"t":"ἦν","g":"was","s":"1510","c":"verb"},{"t":"ξηρά","g":"withered","s":"3584","c":"adj"}],"7":[{"t":"δὲ","g":"now","s":"1161","c":"conj"},{"t":"παρετηροῦντο","g":"Were closely watching","s":"3906","c":"verb"},{"t":"αὐτὸν","g":"Him","s":"846","c":"pron"},{"t":"γραμματεῖς","g":"scribes","s":"1122","c":"noun"},{"t":"καὶ","g":"and","s":"2532","c":"conj"},{"t":"Φαρισαῖοι","g":"Pharisees","s":"5330","c":"noun"},{"t":"εἰ","g":"whether","s":"1487","c":"ptcl"},{"t":"ἐν","g":"on","s":"1722","c":"prep"},{"t":"σαββάτῳ","g":"Sabbath","s":"4521","c":"noun"},{"t":"θεραπεύει","g":"He will heal","s":"2323","c":"verb"},{"t":"ἵνα","g":"that","s":"2443","c":"conj"},{"t":"εὕρωσιν","g":"they might find [reason]","s":"2147","c":"verb"},{"t":"κατηγορεῖν","g":"to accuse","s":"2723","c":"verb"},{"t":"αὐτοῦ","g":"Him","s":"846","c":"pron"}],"8":[{"t":"δὲ","g":"now","s":"1161","c":"conj"},{"t":"αὐτὸς","g":"He","s":"846","c":"pron"},{"t":"ᾔδει","g":"knew","s":"1492","c":"verb"},{"t":"διαλογισμοὺς","g":"thoughts","s":"1261","c":"noun"},{"t":"αὐτῶν","g":"of them","s":"846","c":"pron"},{"t":"δὲ","g":"now","s":"1161","c":"conj"},{"t":"εἶπεν","g":"He said","s":"3004","c":"verb"},{"t":"ἀνδρὶ","g":"man","s":"435","c":"noun"},{"t":"ξηρὰν","g":"withered","s":"3584","c":"adj"},{"t":"ἔχοντι","g":"having","s":"2192","c":"verb"},{"t":"χεῖρα","g":"hand","s":"5495","c":"noun"},{"t":"Ἔγειρε","g":"Arise","s":"1453","c":"verb"},{"t":"καὶ","g":"and","s":"2532","c":"conj"},{"t":"στῆθι","g":"stand","s":"2476","c":"verb"},{"t":"εἰς","g":"in","s":"1519","c":"prep"},{"t":"μέσον","g":"midst","s":"3319","c":"adj"}],"9":[{"t":"δὲ","g":"then","s":"1161","c":"conj"},{"t":"εἶπεν","g":"Said","s":"3004","c":"verb"},{"t":"Ἰησοῦς","g":"Jesus","s":"2424","c":"noun"},{"t":"πρὸς","g":"to","s":"4314","c":"prep"},{"t":"αὐτούς","g":"them","s":"846","c":"pron"},{"t":"Ἐπερωτῶ","g":"I ask","s":"1905","c":"verb"},{"t":"ὑμᾶς","g":"you","s":"4771","c":"pron"},{"t":"εἰ","g":"whether","s":"1487","c":"ptcl"},{"t":"ἔξεστιν","g":"it is lawful","s":"1832","c":"verb"},{"t":"σαββάτῳ","g":"Sabbath","s":"4521","c":"noun"},{"t":"ἀγαθοποιῆσαι","g":"to do good","s":"15","c":"verb"},{"t":"ἢ","g":"or","s":"2228","c":"conj"},{"t":"κακοποιῆσαι","g":"to do evil","s":"2554","c":"verb"},{"t":"ψυχὴν","g":"Life","s":"5590","c":"noun"},{"t":"σῶσαι","g":"to save","s":"4982","c":"verb"},{"t":"ἢ","g":"or","s":"2228","c":"conj"},{"t":"ἀπολέσαι","g":"to destroy","s":"622","c":"verb"}],"10":[{"t":"καὶ","g":"And","s":"2532","c":"conj"},{"t":"περιβλεψάμενος","g":"having looked around","s":"4017","c":"verb"},{"t":"πάντας","g":"all","s":"3956","c":"adj"},{"t":"αὐτοὺς","g":"on them","s":"846","c":"pron"},{"t":"εἶπεν","g":"He said","s":"3004","c":"verb"},{"t":"αὐτῷ","g":"to him","s":"846","c":"pron"},{"t":"Ἔκτεινον","g":"Stretch out","s":"1614","c":"verb"},{"t":"χεῖρά","g":"hand","s":"5495","c":"noun"},{"t":"σου","g":"of you","s":"4771","c":"pron"}],"11":[{"t":"δὲ","g":"then","s":"1161","c":"conj"},{"t":"αὐτοὶ","g":"They themselves","s":"846","c":"pron"},{"t":"ἐπλήσθησαν","g":"were filled","s":"4130","c":"verb"},{"t":"ἀνοίας","g":"with rage","s":"454","c":"noun"},{"t":"καὶ","g":"and","s":"2532","c":"conj"},{"t":"διελάλουν","g":"were discussing","s":"1255","c":"verb"},{"t":"πρὸς","g":"with","s":"4314","c":"prep"},{"t":"ἀλλήλους","g":"one another","s":"240","c":"pron"},{"t":"τί","g":"what","s":"5101","c":"pron"},{"t":"ποιήσαιεν","g":"they might do","s":"4160","c":"verb"},{"t":"Ἰησοῦ","g":"to Jesus","s":"2424","c":"noun"}],"12":[{"t":"δὲ","g":"then","s":"1161","c":"conj"},{"t":"Ἐγένετο","g":"It came to pass","s":"1096","c":"verb"},{"t":"ἐν","g":"in","s":"1722","c":"prep"},{"t":"ἡμέραις","g":"days","s":"2250","c":"noun"},{"t":"ταύταις","g":"those","s":"3778","c":"pron"},{"t":"ἐξελθεῖν","g":"went out","s":"1831","c":"verb"},{"t":"αὐτὸν","g":"He","s":"846","c":"pron"},{"t":"εἰς","g":"to","s":"1519","c":"prep"},{"t":"ὄρος","g":"mountain","s":"3735","c":"noun"},{"t":"προσεύξασθαι","g":"to pray","s":"4336","c":"verb"},{"t":"καὶ","g":"and","s":"2532","c":"conj"},{"t":"ἦν","g":"He was","s":"1510","c":"verb"},{"t":"διανυκτερεύων","g":"spending the night","s":"1273","c":"verb"},{"t":"ἐν","g":"in","s":"1722","c":"prep"},{"t":"προσευχῇ","g":"prayer","s":"4335","c":"noun"},{"t":"Θεοῦ","g":"to God","s":"2316","c":"noun"}],"13":[{"t":"καὶ","g":"And","s":"2532","c":"conj"},{"t":"ὅτε","g":"when","s":"3753","c":"conj"},{"t":"ἐγένετο","g":"it became","s":"1096","c":"verb"},{"t":"ἡμέρα","g":"day","s":"2250","c":"noun"},{"t":"προσεφώνησεν","g":"He called to [Him]","s":"4377","c":"verb"},{"t":"μαθητὰς","g":"disciples","s":"3101","c":"noun"},{"t":"αὐτοῦ","g":"of Him","s":"846","c":"pron"},{"t":"καὶ","g":"also","s":"2532","c":"conj"},{"t":"ἐκλεξάμενος","g":"having chosen out","s":"1586","c":"verb"},{"t":"ἀπ’","g":"from","s":"575","c":"prep"},{"t":"αὐτῶν","g":"them","s":"846","c":"pron"},{"t":"δώδεκα","g":"twelve","s":"1427","c":"num"},{"t":"οὓς","g":"whom","s":"3739","c":"pron"},{"t":"καὶ","g":"also","s":"2532","c":"adv"},{"t":"ἀποστόλους","g":"apostles","s":"652","c":"noun"},{"t":"ὠνόμασεν","g":"He named","s":"3687","c":"verb"},{"t":"Σίμωνα","g":"Simon","s":"4613","c":"noun"},{"t":"ὃν","g":"whom","s":"3739","c":"pron"},{"t":"καὶ","g":"also","s":"2532","c":"adv"},{"t":"ὠνόμασεν","g":"He named","s":"3687","c":"verb"},{"t":"Πέτρον","g":"Peter","s":"4074","c":"noun"},{"t":"καὶ","g":"and","s":"2532","c":"conj"},{"t":"Ἀνδρέαν","g":"Andrew","s":"406","c":"noun"},{"t":"ἀδελφὸν","g":"brother","s":"80","c":"noun"},{"t":"αὐτοῦ","g":"of him","s":"846","c":"pron"},{"t":"καὶ","g":"and","s":"2532","c":"conj"},{"t":"Ἰάκωβον","g":"James","s":"2385","c":"noun"},{"t":"καὶ","g":"and","s":"2532","c":"conj"},{"t":"Ἰωάνην","g":"John","s":"2491","c":"noun"},{"t":"καὶ","g":"and","s":"2532","c":"conj"},{"t":"Φίλιππον","g":"Philip","s":"5376","c":"noun"},{"t":"καὶ","g":"and","s":"2532","c":"conj"},{"t":"Βαρθολομαῖον","g":"Bartholomew","s":"918","c":"noun"},{"t":"καὶ","g":"and","s":"2532","c":"conj"},{"t":"Μαθθαῖον","g":"Matthew","s":"3156","c":"noun"},{"t":"καὶ","g":"and","s":"2532","c":"conj"},{"t":"Θωμᾶν","g":"Thomas","s":"2381","c":"noun"},{"t":"καὶ","g":"and","s":"2532","c":"conj"},{"t":"Ἰάκωβον","g":"James","s":"2385","c":"noun"},{"t":"Ἀλφαίου","g":"[son of] Alphaeus","s":"256","c":"noun"},{"t":"καὶ","g":"and","s":"2532","c":"conj"},{"t":"Σίμωνα","g":"Simon","s":"4613","c":"noun"},{"t":"καλούμενον","g":"called","s":"2564","c":"verb"},{"t":"Ζηλωτὴν","g":"Zealot","s":"2207","c":"noun"},{"t":"καὶ","g":"and","s":"2532","c":"conj"},{"t":"Ἰούδαν","g":"Judas [son]","s":"2455","c":"noun"},{"t":"Ἰακώβου","g":"of James","s":"2385","c":"noun"},{"t":"καὶ","g":"and","s":"2532","c":"conj"},{"t":"Ἰούδαν","g":"Judas","s":"2455","c":"noun"},{"t":"Ἰσκαριὼθ","g":"Iscariot","s":"2469","c":"noun"},{"t":"ὃς","g":"who","s":"3739","c":"pron"},{"t":"ἐγένετο","g":"became","s":"1096","c":"verb"},{"t":"προδότης","g":"[the] betrayer","s":"4273","c":"noun"}],"17":[{"t":"καὶ","g":"And","s":"2532","c":"conj"},{"t":"καταβὰς","g":"having descended","s":"2597","c":"verb"},{"t":"μετ’","g":"with","s":"3326","c":"prep"},{"t":"αὐτῶν","g":"them","s":"846","c":"pron"},{"t":"ἔστη","g":"He stood","s":"2476","c":"verb"},{"t":"ἐπὶ","g":"on","s":"1909","c":"prep"},{"t":"τόπου","g":"a place","s":"5117","c":"noun"},{"t":"πεδινοῦ","g":"level","s":"3977","c":"adj"},{"t":"καὶ","g":"and","s":"2532","c":"conj"},{"t":"ὄχλος","g":"a crowd","s":"3793","c":"noun"},{"t":"πολὺς","g":"large","s":"4183","c":"adj"},{"t":"μαθητῶν","g":"of disciples","s":"3101","c":"noun"},{"t":"αὐτοῦ","g":"of Him","s":"846","c":"pron"},{"t":"καὶ","g":"and","s":"2532","c":"conj"},{"t":"πλῆθος","g":"a multitude","s":"4128","c":"noun"},{"t":"πολὺ","g":"great","s":"4183","c":"adj"},{"t":"λαοῦ","g":"people","s":"2992","c":"noun"},{"t":"ἀπὸ","g":"from","s":"575","c":"prep"},{"t":"πάσης","g":"all","s":"3956","c":"adj"},{"t":"Ἰουδαίας","g":"Judea","s":"2449","c":"noun"},{"t":"καὶ","g":"and","s":"2532","c":"conj"},{"t":"Ἱερουσαλὴμ","g":"Jerusalem","s":"2419","c":"noun"},{"t":"καὶ","g":"and","s":"2532","c":"conj"},{"t":"παραλίου","g":"sea coast","s":"3882","c":"adj"},{"t":"Τύρου","g":"of Tyre","s":"5184","c":"noun"},{"t":"καὶ","g":"and","s":"2532","c":"conj"},{"t":"Σιδῶνος","g":"Sidon","s":"4605","c":"noun"},{"t":"οἳ","g":"who","s":"3739","c":"pron"},{"t":"ἦλθον","g":"came","s":"2064","c":"verb"},{"t":"ἀκοῦσαι","g":"to hear","s":"191","c":"verb"},{"t":"αὐτοῦ","g":"Him","s":"846","c":"pron"},{"t":"καὶ","g":"and","s":"2532","c":"conj"},{"t":"ἰαθῆναι","g":"to be healed","s":"2390","c":"verb"},{"t":"ἀπὸ","g":"of","s":"575","c":"prep"},{"t":"νόσων","g":"diseases","s":"3554","c":"noun"},{"t":"αὐτῶν","g":"of them","s":"846","c":"pron"}],"18":[{"t":"καὶ","g":"And","s":"2532","c":"conj"},{"t":"ἐνοχλούμενοι","g":"troubled","s":"1776","c":"verb"},{"t":"ἀπὸ","g":"with","s":"575","c":"prep"},{"t":"πνευμάτων","g":"spirits","s":"4151","c":"noun"},{"t":"ἀκαθάρτων","g":"unclean","s":"169","c":"adj"},{"t":"ἐθεραπεύοντο","g":"were healed","s":"2323","c":"verb"}],"19":[{"t":"καὶ","g":"And","s":"2532","c":"conj"},{"t":"πᾶς","g":"all","s":"3956","c":"adj"},{"t":"ὄχλος","g":"multitude","s":"3793","c":"noun"},{"t":"ἐζήτουν","g":"were seeking","s":"2212","c":"verb"},{"t":"ἅπτεσθαι","g":"to touch","s":"680","c":"verb"},{"t":"αὐτοῦ","g":"Him","s":"846","c":"pron"},{"t":"ὅτι","g":"because","s":"3754","c":"conj"},{"t":"δύναμις","g":"power","s":"1411","c":"noun"},{"t":"παρ’","g":"from","s":"3844","c":"prep"},{"t":"αὐτοῦ","g":"Him","s":"846","c":"pron"},{"t":"ἐξήρχετο","g":"was going out","s":"1831","c":"verb"},{"t":"καὶ","g":"and","s":"2532","c":"conj"},{"t":"ἰᾶτο","g":"healing","s":"2390","c":"verb"},{"t":"πάντας","g":"all","s":"3956","c":"adj"}],"20":[{"t":"Καὶ","g":"And","s":"2532","c":"conj"},{"t":"αὐτὸς","g":"He","s":"846","c":"pron"},{"t":"ἐπάρας","g":"having lifted up","s":"1869","c":"verb"},{"t":"ὀφθαλμοὺς","g":"gaze","s":"3788","c":"noun"},{"t":"αὐτοῦ","g":"of Him","s":"846","c":"pron"},{"t":"εἰς","g":"upon","s":"1519","c":"prep"},{"t":"μαθητὰς","g":"disciples","s":"3101","c":"noun"},{"t":"αὐτοῦ","g":"of Him","s":"846","c":"pron"},{"t":"ἔλεγεν","g":"was saying","s":"3004","c":"verb"},{"t":"Μακάριοι","g":"Blessed [are]","s":"3107","c":"adj"},{"t":"πτωχοί","g":"poor","s":"4434","c":"adj"},{"t":"ὅτι","g":"for","s":"3754","c":"conj"},{"t":"ὑμετέρα","g":"yours","s":"5212","c":"adj"},{"t":"ἐστὶν","g":"is","s":"1510","c":"verb"},{"t":"βασιλεία","g":"kingdom","s":"932","c":"noun"},{"t":"Θεοῦ","g":"of God","s":"2316","c":"noun"}],"21":[{"t":"μακάριοι","g":"Blessed [are]","s":"3107","c":"adj"},{"t":"πεινῶντες","g":"hungering","s":"3983","c":"verb"},{"t":"νῦν","g":"now","s":"3568","c":"adv"},{"t":"ὅτι","g":"for","s":"3754","c":"conj"},{"t":"χορτασθήσεσθε","g":"you will be filled","s":"5526","c":"verb"}],"22":[{"t":"μακάριοί","g":"Blessed","s":"3107","c":"adj"},{"t":"ἐστε","g":"are you","s":"1510","c":"verb"},{"t":"ὅταν","g":"when","s":"3752","c":"conj"},{"t":"μισήσωσιν","g":"shall hate","s":"3404","c":"verb"},{"t":"ὑμᾶς","g":"you","s":"4771","c":"pron"},{"t":"ἄνθρωποι","g":"men","s":"444","c":"noun"},{"t":"καὶ","g":"and","s":"2532","c":"conj"},{"t":"ὅταν","g":"when","s":"3752","c":"conj"},{"t":"ἀφορίσωσιν","g":"they shall exclude","s":"873","c":"verb"},{"t":"ὑμᾶς","g":"you","s":"4771","c":"pron"},{"t":"καὶ","g":"and","s":"2532","c":"conj"},{"t":"ὀνειδίσωσιν","g":"shall insult [you]","s":"3679","c":"verb"},{"t":"καὶ","g":"and","s":"2532","c":"conj"},{"t":"ἐκβάλωσιν","g":"shall cast out","s":"1544","c":"verb"},{"t":"ὄνομα","g":"name","s":"3686","c":"noun"},{"t":"ὑμῶν","g":"of you","s":"4771","c":"pron"},{"t":"ὡς","g":"as","s":"5613","c":"conj"},{"t":"πονηρὸν","g":"evil","s":"4190","c":"adj"},{"t":"ἕνεκα","g":"on account of","s":"1752","c":"prep"},{"t":"Υἱοῦ","g":"Son","s":"5207","c":"noun"},{"t":"ἀνθρώπου","g":"of Man","s":"444","c":"noun"}],"23":[{"t":"χάρητε","g":"Rejoice","s":"5463","c":"verb"},{"t":"ἐν","g":"in","s":"1722","c":"prep"},{"t":"ἐκείνῃ","g":"that","s":"1565","c":"pron"},{"t":"ἡμέρᾳ","g":"day","s":"2250","c":"noun"},{"t":"καὶ","g":"and","s":"2532","c":"conj"},{"t":"σκιρτήσατε","g":"leap for joy","s":"4640","c":"verb"},{"t":"γὰρ","g":"for","s":"1063","c":"conj"},{"t":"ἰδοὺ","g":"behold","s":"3708","c":"verb"},{"t":"μισθὸς","g":"reward","s":"3408","c":"noun"},{"t":"ὑμῶν","g":"of you","s":"4771","c":"pron"},{"t":"πολὺς","g":"[is] great","s":"4183","c":"adj"},{"t":"ἐν","g":"in","s":"1722","c":"prep"},{"t":"οὐρανῷ","g":"heaven","s":"3772","c":"noun"}],"24":[{"t":"Πλὴν","g":"But","s":"4133","c":"conj"},{"t":"οὐαὶ","g":"woe","s":"3759","c":"ptcl"},{"t":"ὑμῖν","g":"to you","s":"4771","c":"pron"},{"t":"πλουσίοις","g":"rich","s":"4145","c":"adj"},{"t":"ὅτι","g":"for","s":"3754","c":"conj"},{"t":"ἀπέχετε","g":"you are receiving","s":"568","c":"verb"},{"t":"παράκλησιν","g":"comfort","s":"3874","c":"noun"},{"t":"ὑμῶν","g":"of you","s":"4771","c":"pron"}],"25":[{"t":"οὐαὶ","g":"Woe","s":"3759","c":"ptcl"},{"t":"ὑμῖν","g":"to you","s":"4771","c":"pron"},{"t":"ἐμπεπλησμένοι","g":"having been filled","s":"1705","c":"verb"},{"t":"νῦν","g":"now","s":"3568","c":"adv"},{"t":"ὅτι","g":"for","s":"3754","c":"conj"},{"t":"πεινάσετε","g":"you will hunger","s":"3983","c":"verb"}],"26":[{"t":"οὐαὶ","g":"Woe to you","s":"3759","c":"ptcl"},{"t":"ὅταν","g":"when","s":"3752","c":"conj"},{"t":"καλῶς","g":"well","s":"2573","c":"adv"},{"t":"ὑμᾶς","g":"of you","s":"4771","c":"pron"},{"t":"εἴπωσιν","g":"speak","s":"3004","c":"verb"},{"t":"πάντες","g":"all","s":"3956","c":"adj"},{"t":"ἄνθρωποι","g":"men","s":"444","c":"noun"},{"t":"γὰρ","g":"for","s":"1063","c":"conj"},{"t":"κατὰ","g":"according to","s":"2596","c":"prep"},{"t":"αὐτὰ","g":"of them","s":"846","c":"pron"},{"t":"ἐποίουν","g":"used to treat","s":"4160","c":"verb"},{"t":"ψευδοπροφήταις","g":"false prophets","s":"5578","c":"noun"},{"t":"πατέρες","g":"fathers","s":"3962","c":"noun"},{"t":"αὐτῶν","g":"likewise","s":"846","c":"pron"}],"27":[{"t":"Ἀλλὰ","g":"But","s":"235","c":"conj"},{"t":"λέγω","g":"I say","s":"3004","c":"verb"},{"t":"ὑμῖν","g":"to you","s":"4771","c":"pron"},{"t":"ἀκούουσιν","g":"hearing","s":"191","c":"verb"},{"t":"Ἀγαπᾶτε","g":"Love","s":"25","c":"verb"},{"t":"ἐχθροὺς","g":"enemies","s":"2190","c":"adj"},{"t":"ὑμῶν","g":"of you","s":"4771","c":"pron"},{"t":"καλῶς","g":"good","s":"2573","c":"adv"},{"t":"ποιεῖτε","g":"do","s":"4160","c":"verb"},{"t":"μισοῦσιν","g":"hating","s":"3404","c":"verb"},{"t":"ὑμᾶς","g":"you","s":"4771","c":"pron"},{"t":"εὐλογεῖτε","g":"bless","s":"2127","c":"verb"},{"t":"καταρωμένους","g":"cursing","s":"2672","c":"verb"},{"t":"ὑμᾶς","g":"you","s":"4771","c":"pron"},{"t":"προσεύχεσθε","g":"pray","s":"4336","c":"verb"},{"t":"περὶ","g":"for","s":"4012","c":"prep"},{"t":"ἐπηρεαζόντων","g":"mistreating","s":"1908","c":"verb"},{"t":"ὑμᾶς","g":"you","s":"4771","c":"pron"}],"29":[{"t":"τύπτοντί","g":"striking","s":"5180","c":"verb"},{"t":"σε","g":"you","s":"4771","c":"pron"},{"t":"ἐπὶ","g":"on","s":"1909","c":"prep"},{"t":"σιαγόνα","g":"cheek","s":"4600","c":"noun"},{"t":"πάρεχε","g":"offer","s":"3930","c":"verb"},{"t":"καὶ","g":"also","s":"2532","c":"adv"},{"t":"ἄλλην","g":"other","s":"243","c":"adj"},{"t":"καὶ","g":"and","s":"2532","c":"conj"},{"t":"ἀπὸ","g":"from","s":"575","c":"prep"},{"t":"αἴροντός","g":"taking away","s":"142","c":"verb"},{"t":"σου","g":"your","s":"4771","c":"pron"},{"t":"ἱμάτιον","g":"cloak","s":"2440","c":"noun"},{"t":"καὶ","g":"also","s":"2532","c":"adv"},{"t":"χιτῶνα","g":"tunic","s":"5509","c":"noun"},{"t":"μὴ","g":"not","s":"3361","c":"adv"},{"t":"κωλύσῃς","g":"do withhold","s":"2967","c":"verb"}],"30":[{"t":"παντὶ","g":"To everyone","s":"3956","c":"adj"},{"t":"αἰτοῦντί","g":"asking","s":"154","c":"verb"},{"t":"σε","g":"you","s":"4771","c":"pron"},{"t":"δίδου","g":"give","s":"1325","c":"verb"},{"t":"καὶ","g":"and","s":"2532","c":"conj"},{"t":"ἀπὸ","g":"from","s":"575","c":"prep"},{"t":"αἴροντος","g":"taking away","s":"142","c":"verb"},{"t":"σὰ","g":"yours","s":"4674","c":"adj"},{"t":"μὴ","g":"not","s":"3361","c":"adv"},{"t":"ἀπαίτει","g":"ask [it] back","s":"523","c":"verb"}],"31":[{"t":"καὶ","g":"And","s":"2532","c":"conj"},{"t":"καθὼς","g":"as","s":"2531","c":"conj"},{"t":"θέλετε","g":"you desire","s":"2309","c":"verb"},{"t":"ἵνα","g":"that","s":"2443","c":"conj"},{"t":"ποιῶσιν","g":"should do","s":"4160","c":"verb"},{"t":"ὑμῖν","g":"to you","s":"4771","c":"pron"},{"t":"ἄνθρωποι","g":"men","s":"444","c":"noun"},{"t":"ποιεῖτε","g":"do","s":"4160","c":"verb"},{"t":"αὐτοῖς","g":"to them","s":"846","c":"pron"},{"t":"ὁμοίως","g":"likewise","s":"3668","c":"adv"}],"32":[{"t":"καὶ","g":"And","s":"2532","c":"conj"},{"t":"εἰ","g":"if","s":"1487","c":"conj"},{"t":"ἀγαπᾶτε","g":"you love","s":"25","c":"verb"},{"t":"ἀγαπῶντας","g":"loving","s":"25","c":"verb"},{"t":"ὑμᾶς","g":"you","s":"4771","c":"pron"},{"t":"ποία","g":"what","s":"4169","c":"pron"},{"t":"χάρις","g":"credit","s":"5485","c":"noun"},{"t":"ὑμῖν","g":"to you","s":"4771","c":"pron"},{"t":"ἐστίν","g":"is it","s":"1510","c":"verb"},{"t":"γὰρ","g":"for","s":"1063","c":"conj"},{"t":"καὶ","g":"Even","s":"2532","c":"adv"},{"t":"ἁμαρτωλοὶ","g":"sinners","s":"268","c":"adj"},{"t":"ἀγαπῶντας","g":"loving","s":"25","c":"verb"},{"t":"αὐτοὺς","g":"them","s":"846","c":"pron"},{"t":"ἀγαπῶσιν","g":"love","s":"25","c":"verb"}],"33":[{"t":"γὰρ","g":"for","s":"1063","c":"conj"},{"t":"ἐὰν","g":"if","s":"1437","c":"conj"},{"t":"καὶ","g":"And","s":"2532","c":"adv"},{"t":"ἀγαθοποιῆτε","g":"you do good","s":"15","c":"verb"},{"t":"ἀγαθοποιοῦντας","g":"doing good to","s":"15","c":"verb"},{"t":"ὑμᾶς","g":"you","s":"4771","c":"pron"},{"t":"ποία","g":"what","s":"4169","c":"pron"},{"t":"χάρις","g":"credit","s":"5485","c":"noun"},{"t":"ὑμῖν","g":"to you","s":"4771","c":"pron"},{"t":"ἐστίν","g":"is it","s":"1510","c":"verb"},{"t":"καὶ","g":"For even","s":"2532","c":"adv"},{"t":"ἁμαρτωλοὶ","g":"sinners","s":"268","c":"adj"},{"t":"αὐτὸ","g":"same","s":"846","c":"pron"},{"t":"ποιοῦσιν","g":"do","s":"4160","c":"verb"}],"34":[{"t":"καὶ","g":"And","s":"2532","c":"conj"},{"t":"ἐὰν","g":"if","s":"1437","c":"conj"},{"t":"δανίσητε","g":"you lend [to those]","s":"1155","c":"verb"},{"t":"παρ’","g":"from","s":"3844","c":"prep"},{"t":"ὧν","g":"whom","s":"3739","c":"pron"},{"t":"ἐλπίζετε","g":"you expect","s":"1679","c":"verb"},{"t":"λαβεῖν","g":"to receive back","s":"2983","c":"verb"},{"t":"ποία","g":"what","s":"4169","c":"pron"},{"t":"χάρις","g":"credit","s":"5485","c":"noun"},{"t":"ὑμῖν","g":"to you","s":"4771","c":"pron"},{"t":"ἐστίν","g":"is it","s":"1510","c":"verb"},{"t":"καὶ","g":"Even","s":"2532","c":"adv"},{"t":"ἁμαρτωλοὶ","g":"sinners","s":"268","c":"adj"},{"t":"ἁμαρτωλοῖς","g":"to sinners","s":"268","c":"adj"},{"t":"δανίζουσιν","g":"lend","s":"1155","c":"verb"},{"t":"ἵνα","g":"that","s":"2443","c":"conj"},{"t":"ἀπολάβωσιν","g":"they might receive","s":"618","c":"verb"},{"t":"ἴσα","g":"same amount","s":"2470","c":"adj"}],"35":[{"t":"πλὴν","g":"But","s":"4133","c":"conj"},{"t":"ἀγαπᾶτε","g":"love","s":"25","c":"verb"},{"t":"ἐχθροὺς","g":"enemies","s":"2190","c":"adj"},{"t":"ὑμῶν","g":"of you","s":"4771","c":"pron"},{"t":"καὶ","g":"and","s":"2532","c":"conj"},{"t":"ἀγαθοποιεῖτε","g":"do good","s":"15","c":"verb"},{"t":"καὶ","g":"and","s":"2532","c":"conj"},{"t":"δανίζετε","g":"lend","s":"1155","c":"verb"},{"t":"μηδὲν","g":"nothing","s":"3367","c":"adj"},{"t":"ἀπελπίζοντες","g":"expecting in return","s":"560","c":"verb"}],"36":[{"t":"Γίνεσθε","g":"Be you","s":"1096","c":"verb"},{"t":"οἰκτίρμονες","g":"merciful","s":"3629","c":"adj"},{"t":"καθὼς","g":"as","s":"2531","c":"conj"},{"t":"Πατὴρ","g":"Father","s":"3962","c":"noun"},{"t":"ὑμῶν","g":"of you","s":"4771","c":"pron"},{"t":"οἰκτίρμων","g":"merciful","s":"3629","c":"adj"},{"t":"ἐστίν","g":"is","s":"1510","c":"verb"}],"37":[{"t":"καὶ","g":"And","s":"2532","c":"conj"},{"t":"μὴ","g":"not","s":"3361","c":"adv"},{"t":"κρίνετε","g":"judge","s":"2919","c":"verb"},{"t":"καὶ","g":"that","s":"2532","c":"conj"},{"t":"οὐ","g":"no","s":"3756","c":"adv"},{"t":"μὴ","g":"not","s":"3361","c":"adv"},{"t":"κριθῆτε","g":"you should be judged","s":"2919","c":"verb"}],"38":[{"t":"δίδοτε","g":"Give","s":"1325","c":"verb"},{"t":"καὶ","g":"and","s":"2532","c":"conj"},{"t":"δοθήσεται","g":"it will be given","s":"1325","c":"verb"},{"t":"ὑμῖν","g":"to you","s":"4771","c":"pron"}],"39":[{"t":"δὲ","g":"then","s":"1161","c":"conj"},{"t":"Εἶπεν","g":"He spoke","s":"3004","c":"verb"},{"t":"καὶ","g":"also","s":"2532","c":"adv"},{"t":"παραβολὴν","g":"a parable","s":"3850","c":"noun"},{"t":"αὐτοῖς","g":"to them","s":"846","c":"pron"}],"40":[{"t":"οὐκ","g":"Not","s":"3756","c":"adv"},{"t":"ἔστιν","g":"is","s":"1510","c":"verb"},{"t":"μαθητὴς","g":"a disciple","s":"3101","c":"noun"},{"t":"ὑπὲρ","g":"above","s":"5228","c":"prep"},{"t":"διδάσκαλον","g":"teacher","s":"1320","c":"noun"},{"t":"δὲ","g":"however","s":"1161","c":"conj"},{"t":"κατηρτισμένος","g":"fully trained","s":"2675","c":"verb"},{"t":"πᾶς","g":"everyone","s":"3956","c":"adj"},{"t":"ἔσται","g":"will be","s":"1510","c":"verb"},{"t":"ὡς","g":"like","s":"5613","c":"conj"},{"t":"διδάσκαλος","g":"teacher","s":"1320","c":"noun"},{"t":"αὐτοῦ","g":"of him","s":"846","c":"pron"}],"41":[{"t":"δὲ","g":"now","s":"1161","c":"conj"},{"t":"Τί","g":"Why","s":"5101","c":"pron"},{"t":"βλέπεις","g":"look you at","s":"991","c":"verb"},{"t":"κάρφος","g":"splinter","s":"2595","c":"noun"},{"t":"ἐν","g":"in","s":"1722","c":"prep"},{"t":"ὀφθαλμῷ","g":"eye","s":"3788","c":"noun"},{"t":"ἀδελφοῦ","g":"brother","s":"80","c":"noun"},{"t":"σου","g":"of you","s":"4771","c":"pron"},{"t":"δὲ","g":"and","s":"1161","c":"conj"},{"t":"δοκὸν","g":"the beam","s":"1385","c":"noun"},{"t":"ἐν","g":"in","s":"1722","c":"prep"},{"t":"ἰδίῳ","g":"own","s":"2398","c":"adj"},{"t":"ὀφθαλμῷ","g":"eye","s":"3788","c":"noun"},{"t":"οὐ","g":"not","s":"3756","c":"adv"},{"t":"κατανοεῖς","g":"notice","s":"2657","c":"verb"}],"42":[{"t":"πῶς","g":"How","s":"4459","c":"adv"},{"t":"δύνασαι","g":"are you able","s":"1410","c":"verb"},{"t":"λέγειν","g":"to say","s":"3004","c":"verb"},{"t":"ἀδελφῷ","g":"brother","s":"80","c":"noun"},{"t":"σου","g":"of you","s":"4771","c":"pron"},{"t":"Ἀδελφέ","g":"Brother","s":"80","c":"noun"},{"t":"ἄφες","g":"let [that]","s":"863","c":"verb"},{"t":"ἐκβάλω","g":"I might cast out","s":"1544","c":"verb"},{"t":"κάρφος","g":"splinter","s":"2595","c":"noun"},{"t":"ἐν","g":"in","s":"1722","c":"prep"},{"t":"ὀφθαλμῷ","g":"eye","s":"3788","c":"noun"},{"t":"σου","g":"of you","s":"4771","c":"pron"},{"t":"αὐτὸς","g":"yourself","s":"846","c":"pron"},{"t":"ἐν","g":"in","s":"1722","c":"prep"},{"t":"ὀφθαλμῷ","g":"eye","s":"3788","c":"noun"},{"t":"σοῦ","g":"of you","s":"4771","c":"pron"},{"t":"δοκὸν","g":"beam","s":"1385","c":"noun"},{"t":"οὐ","g":"not","s":"3756","c":"adv"},{"t":"βλέπων","g":"seeing","s":"991","c":"verb"}],"43":[{"t":"γάρ","g":"for","s":"1063","c":"conj"},{"t":"Οὐ","g":"No","s":"3756","c":"adv"},{"t":"ἐστιν","g":"there is","s":"1510","c":"verb"},{"t":"ποιοῦν","g":"producing","s":"4160","c":"verb"},{"t":"δένδρον","g":"tree","s":"1186","c":"noun"},{"t":"καλὸν","g":"good","s":"2570","c":"adj"},{"t":"καρπὸν","g":"fruit","s":"2590","c":"noun"},{"t":"σαπρόν","g":"bad","s":"4550","c":"adj"},{"t":"οὐδὲ","g":"nor","s":"3761","c":"conj"},{"t":"πάλιν","g":"again","s":"3825","c":"adv"},{"t":"δένδρον","g":"a tree","s":"1186","c":"noun"},{"t":"σαπρὸν","g":"bad","s":"4550","c":"adj"},{"t":"ποιοῦν","g":"producing","s":"4160","c":"verb"},{"t":"καρπὸν","g":"fruit","s":"2590","c":"noun"},{"t":"καλόν","g":"good","s":"2570","c":"adj"}],"44":[{"t":"γὰρ","g":"for","s":"1063","c":"conj"},{"t":"ἕκαστον","g":"Each","s":"1538","c":"adj"},{"t":"δένδρον","g":"tree","s":"1186","c":"noun"},{"t":"ἐκ","g":"by","s":"1537","c":"prep"},{"t":"ἰδίου","g":"own","s":"2398","c":"adj"},{"t":"καρποῦ","g":"fruit","s":"2590","c":"noun"},{"t":"γινώσκεται","g":"is known","s":"1097","c":"verb"}],"45":[{"t":"ἀγαθὸς","g":"good","s":"18","c":"adj"},{"t":"ἄνθρωπος","g":"man","s":"444","c":"noun"},{"t":"ἐκ","g":"out of","s":"1537","c":"prep"},{"t":"ἀγαθοῦ","g":"good","s":"18","c":"adj"},{"t":"θησαυροῦ","g":"treasure","s":"2344","c":"noun"},{"t":"καρδίας","g":"heart","s":"2588","c":"noun"},{"t":"προφέρει","g":"brings forth","s":"4393","c":"verb"},{"t":"ἀγαθόν","g":"good","s":"18","c":"adj"},{"t":"καὶ","g":"and","s":"2532","c":"conj"},{"t":"πονηρὸς","g":"evil","s":"4190","c":"adj"},{"t":"ἐκ","g":"out of","s":"1537","c":"prep"},{"t":"πονηροῦ","g":"evil","s":"4190","c":"adj"},{"t":"προφέρει","g":"brings forth","s":"4393","c":"verb"},{"t":"πονηρόν","g":"evil","s":"4190","c":"adj"},{"t":"γὰρ","g":"for","s":"1063","c":"conj"},{"t":"ἐκ","g":"Out of","s":"1537","c":"prep"},{"t":"περισσεύματος","g":"the abundance","s":"4051","c":"noun"},{"t":"καρδίας","g":"of his heart","s":"2588","c":"noun"},{"t":"λαλεῖ","g":"speaks","s":"2980","c":"verb"},{"t":"στόμα","g":"mouth","s":"4750","c":"noun"},{"t":"αὐτοῦ","g":"of him","s":"846","c":"pron"}],"46":[{"t":"δέ","g":"now","s":"1161","c":"conj"},{"t":"Τί","g":"Why","s":"5101","c":"pron"},{"t":"με","g":"Me","s":"1473","c":"pron"},{"t":"καλεῖτε","g":"do you call","s":"2564","c":"verb"},{"t":"Κύριε","g":"Lord","s":"2962","c":"noun"},{"t":"κύριε","g":"Lord","s":"2962","c":"noun"},{"t":"καὶ","g":"and","s":"2532","c":"conj"},{"t":"οὐ","g":"not","s":"3756","c":"adv"},{"t":"ποιεῖτε","g":"do","s":"4160","c":"verb"},{"t":"ἃ","g":"what","s":"3739","c":"pron"},{"t":"λέγω","g":"I say","s":"3004","c":"verb"}],"47":[{"t":"Πᾶς","g":"Everyone","s":"3956","c":"adj"},{"t":"ἐρχόμενος","g":"is coming","s":"2064","c":"verb"},{"t":"πρός","g":"to","s":"4314","c":"prep"},{"t":"με","g":"Me","s":"1473","c":"pron"},{"t":"καὶ","g":"and","s":"2532","c":"conj"},{"t":"ἀκούων","g":"hearing","s":"191","c":"verb"},{"t":"μου","g":"of Me","s":"1473","c":"pron"},{"t":"λόγων","g":"words","s":"3056","c":"noun"},{"t":"καὶ","g":"and","s":"2532","c":"conj"},{"t":"ποιῶν","g":"doing","s":"4160","c":"verb"},{"t":"αὐτούς","g":"them","s":"846","c":"pron"},{"t":"ὑποδείξω","g":"I will show","s":"5263","c":"verb"},{"t":"ὑμῖν","g":"you","s":"4771","c":"pron"},{"t":"τίνι","g":"whom","s":"5101","c":"pron"},{"t":"ἐστὶν","g":"he is","s":"1510","c":"verb"},{"t":"ὅμοιος","g":"like","s":"3664","c":"adj"}],"48":[{"t":"ὅμοιός","g":"Like","s":"3664","c":"adj"},{"t":"ἐστιν","g":"he is","s":"1510","c":"verb"},{"t":"ἀνθρώπῳ","g":"to a man","s":"444","c":"noun"},{"t":"οἰκοδομοῦντι","g":"building","s":"3618","c":"verb"},{"t":"οἰκίαν","g":"a house","s":"3614","c":"noun"},{"t":"ὃς","g":"who","s":"3739","c":"pron"},{"t":"ἔσκαψεν","g":"dug","s":"4626","c":"verb"},{"t":"καὶ","g":"and","s":"2532","c":"conj"},{"t":"ἐβάθυνεν","g":"deepened","s":"900","c":"verb"},{"t":"καὶ","g":"and","s":"2532","c":"conj"},{"t":"ἔθηκεν","g":"laid","s":"5087","c":"verb"},{"t":"θεμέλιον","g":"a foundation","s":"2310","c":"noun"},{"t":"ἐπὶ","g":"on","s":"1909","c":"prep"},{"t":"πέτραν","g":"rock","s":"4073","c":"noun"}],"49":[{"t":"δὲ","g":"however","s":"1161","c":"conj"},{"t":"ἀκούσας","g":"having heard","s":"191","c":"verb"},{"t":"καὶ","g":"and","s":"2532","c":"conj"},{"t":"μὴ","g":"not","s":"3361","c":"adv"},{"t":"ποιήσας","g":"having done","s":"4160","c":"verb"},{"t":"ὅμοιός","g":"like","s":"3664","c":"adj"},{"t":"ἐστιν","g":"is","s":"1510","c":"verb"},{"t":"ἀνθρώπῳ","g":"to a man","s":"444","c":"noun"},{"t":"οἰκοδομήσαντι","g":"having built","s":"3618","c":"verb"},{"t":"οἰκίαν","g":"a house","s":"3614","c":"noun"},{"t":"ἐπὶ","g":"on","s":"1909","c":"prep"},{"t":"γῆν","g":"ground","s":"1093","c":"noun"},{"t":"χωρὶς","g":"without","s":"5565","c":"prep"},{"t":"θεμελίου","g":"a foundation","s":"2310","c":"noun"},{"t":"ᾗ","g":"on which","s":"3739","c":"pron"},{"t":"προσέρηξεν","g":"burst","s":"4366","c":"verb"},{"t":"ποταμός","g":"stream","s":"4215","c":"noun"},{"t":"καὶ","g":"and","s":"2532","c":"conj"},{"t":"εὐθὺς","g":"immediately","s":"2117","c":"adj"},{"t":"συνέπεσεν","g":"it fell","s":"4098","c":"verb"},{"t":"καὶ","g":"and","s":"2532","c":"conj"},{"t":"ἐγένετο","g":"was","s":"1096","c":"verb"},{"t":"ῥῆγμα","g":"ruin","s":"4485","c":"noun"},{"t":"οἰκίας","g":"house","s":"3614","c":"noun"},{"t":"ἐκείνης","g":"that","s":"1565","c":"pron"},{"t":"μέγα","g":"great","s":"3173","c":"adj"}]}