{"1":[{"t":"תּוֹלְדֹ֣ת","g":"[are].the.accounts","s":"8435","c":"noun","tr":"tôləḏōṯ"},{"t":"בְּנֵי","g":"of.the.sons","s":"1121","c":"noun","tr":"bənê-"},{"t":"נֹ֔חַ","g":"of.Noah","s":"5146","c":"noun","tr":"nōᵃḥ"},{"t":"שֵׁ֖ם","g":"Shem","s":"8035","c":"noun","tr":"šēm"},{"t":"חָ֣ם","g":"Ham","s":"2526","c":"noun","tr":"ḥām"},{"t":"בָּנִ֖ים","g":"sons","s":"1121","c":"noun","tr":"bāniym"},{"t":"אַחַ֥ר","g":"after","s":"0310","c":"prep","tr":"ʾaḥar"}],"2":[{"t":"בְּנֵ֣י","g":"the.sons","s":"1121","c":"noun","tr":"bənēy"},{"t":"יֶ֔פֶת","g":"of.Japheth","s":"3315","c":"noun","tr":"yep̄eṯ"},{"t":"גֹּ֣מֶר","g":"[were].Gomer","s":"1586","c":"noun","tr":"gōmer"}],"3":[{"t":"גֹּ֑מֶר","g":"of.Gomer","s":"1586","c":"noun","tr":"gōmer"},{"t":"אַשְׁכֲּנַ֥ז","g":"[were].Ashkenaz","s":"813","c":"noun","tr":"ʾaškănaz"}],"4":[{"t":"יָוָ֖ן","g":"of.Javan","s":"3120","c":"noun","tr":"yāwān"},{"t":"אֱלִישָׁ֣ה","g":"[were].Elishah","s":"0473","c":"noun","tr":"ʾĕlîšāh"},{"t":"כִּתִּ֖ים","g":"Kittim","s":"3794","c":"noun","tr":"kittiym"}],"5":[{"t":"נִפְרְד֞וּ","g":"they.separated","s":"6504","c":"verb","tr":"nip̄rəḏû"},{"t":"אִיֵּ֤י","g":"the.coastlands","s":"339","c":"noun","tr":"ʾiyyēy"},{"t":"אִ֖ישׁ","g":"each","s":"0376","c":"noun","tr":"ʾiyš"}],"6":[{"t":"חָ֑ם","g":"of.Ham","s":"2526","c":"noun","tr":"ḥām"},{"t":"כּ֥וּשׁ","g":"[were].Cush","s":"3568","c":"noun","tr":"kûš"}],"7":[{"t":"כ֔וּשׁ","g":"of.Cush","s":"3568","c":"noun","tr":"ḵûš"},{"t":"סְבָא֙","g":"[were].Seba","s":"5434","c":"noun","tr":"səḇāʾ"},{"t":"רַעְמָ֖ה","g":"of.Raamah","s":"7484","c":"noun","tr":"raʿmāh"},{"t":"שְׁבָ֥א","g":"[were].Sheba","s":"7614","c":"noun","tr":"šəḇāʾ"}],"8":[{"t":"יָלַ֣ד","g":"he.fathered","s":"3205","c":"verb","tr":"yālaḏ"},{"t":"אֶת","g":"(et)","s":"853","c":"om","tr":"ʾeṯ-"},{"t":"נִמְרֹ֑ד","g":"Nimrod","s":"5248","c":"noun","tr":"nimrōḏ"},{"t":"ה֣וּא","g":"he","s":"1931","c":"pron","tr":"hûʾ"},{"t":"הֵחֵ֔ל","g":"he.began","s":"2490","c":"verb","tr":"hēḥēl"},{"t":"גִּבֹּ֖ר","g":"a.mighty.[man]","s":"1368","c":"adj","tr":"gibbōr"}],"9":[{"t":"הֽוּא","g":"he","s":"1931","c":"pron","tr":"hûʾ-"},{"t":"הָיָ֥ה","g":"he.was","s":"1961","c":"verb","tr":"hāyāh"},{"t":"גִבֹּֽר","g":"a.mighty.[man]","s":"1368","c":"adj","tr":"ḡibbōr-"},{"t":"צַ֖יִד","g":"of.hunting","s":"6718","c":"noun","tr":"ṣayiḏ"},{"t":"יְהוָ֑ה","g":"Yahweh","s":"3068","c":"noun","tr":"yəhwāh"},{"t":"יֵֽאָמַ֔ר","g":"it.is.said","s":"559","c":"verb","tr":"yēʾāmar"},{"t":"גִּבּ֥וֹר","g":"a.mighty.[man]","s":"1368","c":"adj","tr":"gibôr"},{"t":"צַ֖יִד","g":"of.hunting","s":"6718","c":"noun","tr":"ṣayiḏ"},{"t":"יְהוָֽה","g":"Yahweh","s":"3068","c":"noun","tr":"yəhwāh:"}],"10":[{"t":"רֵאשִׁ֤ית","g":"the.beginning","s":"7225","c":"noun","tr":"rēʾšiyṯ"},{"t":"בָּבֶ֔ל","g":"Babel","s":"894","c":"noun","tr":"bāḇel"},{"t":"שִׁנְעָֽר","g":"of.Shinar","s":"8152","c":"noun","tr":"šinʿār:"}],"11":[{"t":"מִן","g":"from","s":"4480","c":"prep","tr":"min-"},{"t":"יָצָ֣א","g":"he.went.forth","s":"3318","c":"verb","tr":"yāṣāʾ"},{"t":"אַשּׁ֑וּר","g":"Assyria","s":"804","c":"noun","tr":"ʾaššûr"},{"t":"אֶת","g":"(et)","s":"853","c":"om","tr":"ʾeṯ-"},{"t":"נִ֣ינְוֵ֔ה","g":"Nineveh","s":"5210","c":"noun","tr":"niynəwēh"},{"t":"כָּֽלַח","g":"Calah","s":"3625","c":"noun","tr":"kālaḥ:"}],"12":[{"t":"רֶ֔סֶן","g":"Resen","s":"7449","c":"noun","tr":"resen"},{"t":"בֵּ֥ין","g":"between","s":"996","c":"prep","tr":"bēyn"},{"t":"נִֽינְוֵ֖ה","g":"Nineveh","s":"5210","c":"noun","tr":"niynəwēh"},{"t":"כָּ֑לַח","g":"Calah","s":"3625","c":"noun","tr":"kālaḥ"},{"t":"הִ֖וא","g":"that","s":"1931a","c":"pron","tr":"hiwʾ"}],"13":[{"t":"יָלַ֞ד","g":"he.fathered","s":"3205","c":"verb","tr":"yālaḏ"},{"t":"אֶת","g":"(et)","s":"853","c":"om","tr":"ʾeṯ-"},{"t":"לוּדִ֧ים","g":"[the].Ludites","s":"3866","c":"noun","tr":"lûḏiym"},{"t":"עֲנָמִ֛ים","g":"[the].Anamites","s":"6047","c":"noun","tr":"ʿănāmiym"},{"t":"לְהָבִ֖ים","g":"[the].Lehabites","s":"3853","c":"noun","tr":"ləhāḇiym"},{"t":"נַפְתֻּחִֽים","g":"[the].Naphtuhites","s":"5320","c":"noun","tr":"nap̄tuḥiym:"}],"14":[{"t":"פַּתְרֻסִ֞ים","g":"[the].Pathrusites","s":"6625","c":"noun","tr":"paṯrusiym"},{"t":"כַּסְלֻחִ֗ים","g":"[the].Casluhites","s":"3695","c":"noun","tr":"kasluḥiym"},{"t":"אֲשֶׁ֨ר","g":"where","s":"834","c":"rel","tr":"ʾăšer"},{"t":"יָצְא֥וּ","g":"they.came.out","s":"3318","c":"verb","tr":"yāṣʾû"},{"t":"פְּלִשְׁתִּ֖ים","g":"[the].Philistines","s":"6430","c":"noun","tr":"pəlištiym"},{"t":"כַּפְתֹּרִֽים","g":"[the].Caphtorites","s":"3732","c":"noun","tr":"kap̄tōriym:"}],"15":[{"t":"יָלַ֛ד","g":"he.fathered","s":"3205","c":"verb","tr":"yālaḏ"},{"t":"אֶת","g":"(et)","s":"853","c":"om","tr":"ʾeṯ-"},{"t":"צִידֹ֥ן","g":"Sidon","s":"6721","c":"noun","tr":"ṣîḏōn"},{"t":"חֵֽת","g":"Heth","s":"2845","c":"noun","tr":"ḥēṯ:"}],"18":[{"t":"נָפֹ֔צוּ","g":"they.were.scattered","s":"6327","c":"verb","tr":"nāp̄ōṣû"},{"t":"מִשְׁפְּח֖וֹת","g":"the.clans","s":"4940","c":"noun","tr":"mišpəḥôṯ"}],"19":[{"t":"גְּב֤וּל","g":"the.border","s":"1366","c":"noun","tr":"gəḇûl"},{"t":"עַד","g":"to","s":"5704","c":"prep","tr":"ʿaḏ-"},{"t":"עַזָּ֑ה","g":"Gaza","s":"5804","c":"noun","tr":"ʿazzāh"},{"t":"עַד","g":"to","s":"5704","c":"prep","tr":"ʿaḏ-"},{"t":"לָֽשַׁע","g":"Lasha","s":"3962","c":"noun","tr":"lāšaʿ:"}],"20":[{"t":"אֵ֣לֶּה","g":"these","s":"428","c":"adj","tr":"ʾēlleh"},{"t":"בְנֵי","g":"[were].the.sons","s":"1121","c":"noun","tr":"ḇənê-"},{"t":"חָ֔ם","g":"of.Ham","s":"2526","c":"noun","tr":"ḥām"}],"21":[{"t":"יֻלַּ֖ד","g":"it.was.born","s":"3205","c":"verb","tr":"yullaḏ"},{"t":"גַּם","g":"also","s":"1571","c":"cj","tr":"gam-"},{"t":"ה֑וּא","g":"he","s":"1931","c":"pron","tr":"hûʾ"},{"t":"אֲבִי֙","g":"the.father","s":"0001","c":"noun","tr":"ʾăḇî"},{"t":"כָּל","g":"of.all","s":"3605","c":"noun","tr":"kol-"},{"t":"בְּנֵי","g":"the.sons","s":"1121","c":"noun","tr":"bənê-"},{"t":"עֵ֔בֶר","g":"of.Eber","s":"5677","c":"noun","tr":"ʿēḇer"},{"t":"אֲחִ֖י","g":"the.brother","s":"0251","c":"noun","tr":"ʾăḥiy"},{"t":"יֶ֥פֶת","g":"of.Japheth","s":"3315","c":"noun","tr":"yep̄eṯ"}],"22":[{"t":"בְּנֵ֥י","g":"the.sons","s":"1121","c":"noun","tr":"bənēy"},{"t":"שֵׁ֖ם","g":"of.Shem","s":"8035","c":"noun","tr":"šēm"},{"t":"עֵילָ֣ם","g":"[were].Elam","s":"5867a","c":"noun","tr":"ʿêlām"}],"23":[{"t":"אֲרָ֑ם","g":"of.Aram","s":"758","c":"noun","tr":"ʾărām"},{"t":"ע֥וּץ","g":"[were].Uz","s":"5780","c":"noun","tr":"ʿûṣ"}],"24":[{"t":"יָלַ֣ד","g":"he.fathered","s":"3205","c":"verb","tr":"yālaḏ"},{"t":"אֶת","g":"(et)","s":"853","c":"om","tr":"ʾeṯ-"},{"t":"שָׁ֑לַח","g":"Shelah","s":"7974","c":"noun","tr":"šālaḥ"},{"t":"יָלַ֥ד","g":"he.fathered","s":"3205","c":"verb","tr":"yālaḏ"},{"t":"אֶת","g":"(et)","s":"853","c":"om","tr":"ʾeṯ-"},{"t":"עֵֽבֶר","g":"Eber","s":"5677","c":"noun","tr":"ʿēḇer:"}],"25":[{"t":"יֻלַּ֖ד","g":"it.was.born","s":"3205","c":"verb","tr":"yullaḏ"},{"t":"שְׁנֵ֣י","g":"two","s":"8147","c":"num","tr":"šənēy"},{"t":"בָנִ֑ים","g":"sons","s":"1121","c":"noun","tr":"ḇāniym"},{"t":"שֵׁ֣ם","g":"the.name","s":"8034","c":"noun","tr":"šēm"},{"t":"פֶּ֗לֶג","g":"[was].Peleg","s":"6389","c":"noun","tr":"peleḡ"},{"t":"כִּ֤י","g":"(dm)","s":"3588","c":"cj","tr":"kiy"},{"t":"נִפְלְגָ֣ה","g":"it.was.divided","s":"6385","c":"verb","tr":"nip̄ləḡāh"},{"t":"יָקְטָֽן","g":"[was].Joktan","s":"3355","c":"noun","tr":"yāqəṭān:"}],"26":[{"t":"יָלַ֔ד","g":"he.fathered","s":"3205","c":"verb","tr":"yālaḏ"},{"t":"אֶת","g":"(et)","s":"853","c":"om","tr":"ʾeṯ-"},{"t":"אַלְמוֹדָ֖ד","g":"Almodad","s":"486","c":"noun","tr":"ʾalmôḏāḏ"},{"t":"שָׁ֑לֶף","g":"Sheleph","s":"8026","c":"noun","tr":"šālep̄"},{"t":"חֲצַרְמָ֖וֶת","g":"Hazarmaveth","s":"2700","c":"noun","tr":"ḥăṣarmāweṯ"},{"t":"יָֽרַח","g":"Jerah","s":"3392","c":"noun","tr":"yāraḥ:"}],"27":[{"t":"הֲדוֹרָ֥ם","g":"Hadoram","s":"1913","c":"noun","tr":"hăḏôrām"},{"t":"אוּזָ֖ל","g":"Uzal","s":"187","c":"noun","tr":"ʾûzāl"},{"t":"דִּקְלָֽה","g":"Diklah","s":"1853","c":"noun","tr":"diqlāh:"}],"28":[{"t":"עוֹבָ֥ל","g":"Obal","s":"5745","c":"noun","tr":"ʿôḇāl"},{"t":"אֲבִֽימָאֵ֖ל","g":"Abimael","s":"39","c":"noun","tr":"ʾăḇiymāʾēl"},{"t":"שְׁבָֽא","g":"Sheba","s":"7614","c":"noun","tr":"šəḇāʾ:"}],"29":[{"t":"אוֹפִ֥ר","g":"Ophir","s":"0211","c":"noun","tr":"ʾôp̄ir"},{"t":"חֲוִילָ֖ה","g":"Havilah","s":"2341","c":"noun","tr":"ḥăwîlāh"},{"t":"יוֹבָ֑ב","g":"Jobab","s":"3103","c":"noun","tr":"yôḇāḇ"},{"t":"כָּל","g":"all","s":"3605","c":"noun","tr":"kol-"},{"t":"אֵ֖לֶּה","g":"these","s":"428","c":"adj","tr":"ʾēlleh"},{"t":"בְּנֵ֥י","g":"[were].the.sons","s":"1121","c":"noun","tr":"bənēy"},{"t":"יָקְטָֽן","g":"of.Joktan","s":"3355","c":"noun","tr":"yāqəṭān:"}],"30":[{"t":"הַ֥ר","g":"the.hill.country","s":"2022","c":"noun","tr":"har"}],"31":[{"t":"אֵ֣לֶּה","g":"these","s":"428","c":"adj","tr":"ʾēlleh"},{"t":"בְנֵי","g":"[were].the.sons","s":"1121","c":"noun","tr":"ḇənê-"},{"t":"שֵׁ֔ם","g":"of.Shem","s":"8035","c":"noun","tr":"šēm"}],"32":[{"t":"אֵ֣לֶּה","g":"these","s":"428","c":"adj","tr":"ʾēlleh"},{"t":"מִשְׁפְּחֹ֧ת","g":"[were].the.clans","s":"4940","c":"noun","tr":"mišpəḥōṯ"},{"t":"בְּנֵי","g":"of.the.sons","s":"1121","c":"noun","tr":"bənê-"},{"t":"נֹ֛חַ","g":"of.Noah","s":"5146","c":"noun","tr":"nōᵃḥ"},{"t":"נִפְרְד֧וּ","g":"they.separated","s":"6504","c":"verb","tr":"nip̄rəḏû"},{"t":"אַחַ֥ר","g":"after","s":"0310","c":"prep","tr":"ʾaḥar"}]}