{"1":[{"t":"עַֽל","g":"on","s":"5921","c":"prep","tr":"ʿal-"},{"t":"מִזְמ֥וֹר","g":"a.psalm","s":"4210","c":"noun","tr":"mizmôr"}],"2":[{"t":"יְֽהוָ֗ה","g":"O.Yahweh","s":"3068","c":"noun","tr":"yəhwāh"},{"t":"אַל","g":"do.not","s":"408","c":"adv","tr":"ʾal-"}],"3":[{"t":"יְהוָה֮","g":"O.Yahweh","s":"3068","c":"noun","tr":"yhwh"},{"t":"כִּ֤י","g":"(dm)","s":"3588","c":"cj","tr":"kiy"},{"t":"אֻמְלַ֫ל","g":"[am].frail","s":"0536","c":"adj","tr":"ʾumlal"},{"t":"אָ֥נִי","g":"I","s":"589","c":"pron","tr":"ʾānî"},{"t":"יְהוָ֑ה","g":"O.Yahweh","s":"3068","c":"noun","tr":"yəhwāh"},{"t":"כִּ֖י","g":"(dm)","s":"3588","c":"cj","tr":"kiy"},{"t":"נִבְהֲל֣וּ","g":"they.are.disturbed","s":"926","c":"verb","tr":"niḇhălû"}],"4":[{"t":"נִבְהֲלָ֣ה","g":"it.is.disturbed","s":"926","c":"verb","tr":"niḇhălāh"},{"t":"מְאֹ֑ד","g":"exceedingly","s":"3966","c":"adv","tr":"məʾōḏ"},{"t":"יְ֝הוָ֗ה","g":"O.Yahweh","s":"3068","c":"noun","tr":"yəhwāh"},{"t":"עַד","g":"until","s":"5704","c":"prep","tr":"ʿaḏ-"},{"t":"מָתָֽי","g":"when?","s":"4970","c":"ptcl","tr":"māṯāy:"}],"5":[{"t":"יְ֭הוָה","g":"O.Yahweh","s":"3068","c":"noun","tr":"yhwh"},{"t":"לְמַ֣עַן","g":"on.account.of","s":"4616","c":"prep","tr":"ləmaʿan"}],"6":[{"t":"כִּ֤י","g":"(dm)","s":"3588","c":"cj","tr":"kiy"},{"t":"אֵ֣ין","g":"there.[is].not","s":"369","c":"adv","tr":"ʾēyn"},{"t":"מִ֣י","g":"who?","s":"4310","c":"pron","tr":"miy"},{"t":"יֽוֹדֶה","g":"will.he.give.thanks","s":"3034","c":"verb","tr":"yôḏeh-"}],"7":[{"t":"יָגַ֤עְתִּי","g":"I.have.become.weary","s":"3021","c":"verb","tr":"yāḡaʿətî"},{"t":"אַשְׂחֶ֣ה","g":"I.make.swim","s":"7811","c":"verb","tr":"ʾaśḥeh"},{"t":"לַ֭יְלָה","g":"night","s":"3915","c":"noun","tr":"layəlâ"},{"t":"אַמְסֶֽה","g":"I.melt","s":"4529","c":"verb","tr":"ʾamseh:"}],"8":[{"t":"עָֽשְׁשָׁ֣ה","g":"it.has.wasted.away","s":"6244","c":"verb","tr":"ʿāšəšāh"},{"t":"עָֽ֝תְקָ֗ה","g":"it.has.grown.weak","s":"6275","c":"verb","tr":"ʿāṯəqāh"}],"9":[{"t":"ס֣וּרוּ","g":"turn.away","s":"5493","c":"verb","tr":"sûrû"},{"t":"כָּל","g":"O.all","s":"3605","c":"noun","tr":"kol-"},{"t":"פֹּ֣עֲלֵי","g":"[those.who].do","s":"6466","c":"verb","tr":"pōʿălê"},{"t":"אָ֑וֶן","g":"(of).wickedness","s":"0205","c":"noun","tr":"ʾāwen"},{"t":"כִּֽי","g":"(dm)","s":"3588","c":"cj","tr":"kiy-"},{"t":"שָׁמַ֥ע","g":"he.has.heard","s":"8085","c":"verb","tr":"šāmaʿ"},{"t":"יְ֝הוָ֗ה","g":"Yahweh","s":"3068","c":"noun","tr":"yəhwāh"},{"t":"ק֣וֹל","g":"the.sound","s":"6963","c":"noun","tr":"qôl"}],"10":[{"t":"שָׁמַ֣ע","g":"he.has.heard","s":"8085","c":"verb","tr":"šāmaʿ"},{"t":"יְ֭הוָה","g":"Yahweh","s":"3068","c":"noun","tr":"yhwh"},{"t":"יְ֝הוָ֗ה","g":"Yahweh","s":"3068","c":"noun","tr":"yəhwāh"},{"t":"יִקָּֽח","g":"he.will.accept","s":"3947","c":"verb","tr":"yiqqāḥ:"}],"11":[{"t":"יֵבֹ֤שׁוּ","g":"they.will.be.ashamed","s":"954","c":"verb","tr":"yēḇōšû"},{"t":"מְ֭אֹד","g":"exceedingly","s":"3966","c":"adv","tr":"məʾōḏ"},{"t":"כָּל","g":"all","s":"3605","c":"noun","tr":"kol-"},{"t":"יָ֝שֻׁ֗בוּ","g":"they.will.turn.back","s":"7725","c":"verb","tr":"yāšuḇû"},{"t":"יֵבֹ֥שׁוּ","g":"they.will.be.ashamed","s":"954","c":"verb","tr":"yēḇōšû"},{"t":"רָֽגַע","g":"a.moment","s":"7281","c":"noun","tr":"rāḡaʿ:"}]}