{"1":[{"ref":"psalms+149:1","label":"Ps 149:1"},{"ref":"psalms+134:2","label":"Ps 134:2"},{"ref":"psalms+29:9","label":"Ps 29:9"},{"ref":"daniel+12:3","label":"Dan 12:3"},{"ref":"ezekiel+10:1","label":"Ezek 10:1"},{"ref":"psalms+102:19","label":"Ps 102:19"},{"ref":"psalms+19:1","label":"Ps 19:1"}],"2":[{"ref":"deuteronomy+3:24","label":"Deut 3:24"},{"ref":"psalms+145:3","label":"Ps 145:3"},{"ref":"psalms+96:4","label":"Ps 96:4"},{"ref":"psalms+145:12","label":"Ps 145:12"}],"3":[{"ref":"psalms+33:2","label":"Ps 33:2"},{"ref":"psalms+149:3","label":"Ps 149:3"},{"ref":"psalms+92:3","label":"Ps 92:3"},{"ref":"numbers+10:10","label":"Num 10:10"},{"ref":"1chronicles+16:42","label":"1 Chr 16:42"},{"ref":"psalms+108:2","label":"Ps 108:2"},{"ref":"1chronicles+15:28","label":"1 Chr 15:28"},{"ref":"1chronicles+15:24","label":"1 Chr 15:24"}],"4":[{"ref":"psalms+149:3","label":"Ps 149:3"},{"ref":"isaiah+38:20","label":"Isa 38:20"},{"ref":"exodus+15:20","label":"Exod 15:20"},{"ref":"psalms+144:9","label":"Ps 144:9"},{"ref":"psalms+92:3","label":"Ps 92:3"},{"ref":"job+30:31","label":"Job 30:31"},{"ref":"job+21:12","label":"Job 21:12"},{"ref":"psalms+33:2","label":"Ps 33:2"}],"5":[{"ref":"1chronicles+15:16","label":"1 Chr 15:16"},{"ref":"1chronicles+25:1","label":"1 Chr 25:1"},{"ref":"1chronicles+15:28","label":"1 Chr 15:28"},{"ref":"1chronicles+15:19","label":"1 Chr 15:19"},{"ref":"1chronicles+25:6","label":"1 Chr 25:6"},{"ref":"2samuel+6:5","label":"2 Sam 6:5"},{"ref":"1chronicles+16:5","label":"1 Chr 16:5"},{"ref":"1chronicles+13:8","label":"1 Chr 13:8"}],"6":[{"ref":"psalms+145:21","label":"Ps 145:21"},{"ref":"revelation+5:13","label":"Rev 5:13"},{"ref":"psalms+103:22","label":"Ps 103:22"},{"ref":"psalms+145:10","label":"Ps 145:10"}]}