{"1":[{"t":"Ἰάκωβος","g":"James","s":"2385","c":"noun"},{"t":"Θεοῦ","g":"of God","s":"2316","c":"noun"},{"t":"καὶ","g":"and","s":"2532","c":"conj"},{"t":"Κυρίου","g":"of [the] Lord","s":"2962","c":"noun"},{"t":"Ἰησοῦ","g":"Jesus","s":"2424","c":"noun"},{"t":"Χριστοῦ","g":"Christ","s":"5547","c":"noun"},{"t":"δοῦλος","g":"a servant","s":"1401","c":"noun"},{"t":"δώδεκα","g":"twelve","s":"1427","c":"num"},{"t":"φυλαῖς","g":"tribes","s":"5443","c":"noun"},{"t":"ἐν","g":"in","s":"1722","c":"prep"},{"t":"Διασπορᾷ","g":"Dispersion","s":"1290","c":"noun"},{"t":"χαίρειν","g":"Greetings","s":"5463","c":"verb"}],"2":[{"t":"ἀδελφοί","g":"brothers","s":"80","c":"noun"},{"t":"μου","g":"of me","s":"1473","c":"pron"},{"t":"Πᾶσαν","g":"All","s":"3956","c":"adj"},{"t":"χαρὰν","g":"joy","s":"5479","c":"noun"},{"t":"ἡγήσασθε","g":"esteem [it]","s":"2233","c":"verb"},{"t":"ὅταν","g":"when","s":"3752","c":"conj"},{"t":"πειρασμοῖς","g":"trials","s":"3986","c":"noun"},{"t":"ποικίλοις","g":"various","s":"4164","c":"adj"},{"t":"περιπέσητε","g":"you might fall into","s":"4045","c":"verb"},{"t":"γινώσκοντες","g":"knowing","s":"1097","c":"verb"},{"t":"ὅτι","g":"that","s":"3754","c":"conj"},{"t":"δοκίμιον","g":"testing","s":"1383","c":"noun"},{"t":"ὑμῶν","g":"of your","s":"4771","c":"pron"},{"t":"πίστεως","g":"faith","s":"4102","c":"noun"},{"t":"κατεργάζεται","g":"produces","s":"2716","c":"verb"},{"t":"ὑπομονήν","g":"endurance","s":"5281","c":"noun"}],"4":[{"t":"δὲ","g":"And","s":"1161","c":"conj"},{"t":"ὑπομονὴ","g":"endurance","s":"5281","c":"noun"},{"t":"ἔργον","g":"work","s":"2041","c":"noun"},{"t":"τέλειον","g":"[its] perfect","s":"5046","c":"adj"},{"t":"ἐχέτω","g":"let have","s":"2192","c":"verb"},{"t":"ἵνα","g":"so that","s":"2443","c":"conj"},{"t":"ἦτε","g":"you may be","s":"1510","c":"verb"},{"t":"τέλειοι","g":"perfect","s":"5046","c":"adj"},{"t":"καὶ","g":"and","s":"2532","c":"conj"},{"t":"ὁλόκληροι","g":"complete","s":"3648","c":"adj"},{"t":"ἐν","g":"in","s":"1722","c":"prep"},{"t":"μηδενὶ","g":"nothing","s":"3367","c":"adj"},{"t":"λειπόμενοι","g":"lacking","s":"3007","c":"verb"}],"5":[{"t":"δέ","g":"now","s":"1161","c":"conj"},{"t":"Εἰ","g":"If","s":"1487","c":"conj"},{"t":"τις","g":"any","s":"5100","c":"pron"},{"t":"ὑμῶν","g":"of you","s":"4771","c":"pron"},{"t":"λείπεται","g":"lacks","s":"3007","c":"verb"},{"t":"σοφίας","g":"wisdom","s":"4678","c":"noun"},{"t":"αἰτείτω","g":"let him ask","s":"154","c":"verb"},{"t":"παρὰ","g":"from","s":"3844","c":"prep"},{"t":"διδόντος","g":"giving","s":"1325","c":"verb"},{"t":"πᾶσιν","g":"to all","s":"3956","c":"adj"},{"t":"ἁπλῶς","g":"generously","s":"574","c":"adv"},{"t":"καὶ","g":"and","s":"2532","c":"conj"},{"t":"μὴ","g":"not","s":"3361","c":"adv"},{"t":"ὀνειδίζοντος","g":"finding fault","s":"3679","c":"verb"},{"t":"Θεοῦ","g":"God","s":"2316","c":"noun"},{"t":"καὶ","g":"and","s":"2532","c":"conj"},{"t":"δοθήσεται","g":"it will be given","s":"1325","c":"verb"},{"t":"αὐτῷ","g":"to him","s":"846","c":"pron"}],"6":[{"t":"δὲ","g":"however","s":"1161","c":"conj"},{"t":"αἰτείτω","g":"Let him ask","s":"154","c":"verb"},{"t":"ἐν","g":"in","s":"1722","c":"prep"},{"t":"πίστει","g":"faith","s":"4102","c":"noun"},{"t":"μηδὲν","g":"nothing","s":"3367","c":"adj"},{"t":"διακρινόμενος","g":"doubting","s":"1252","c":"verb"}],"7":[{"t":"γὰρ","g":"for","s":"1063","c":"conj"},{"t":"μὴ","g":"Not","s":"3361","c":"adv"},{"t":"οἰέσθω","g":"let suppose","s":"3633","c":"verb"},{"t":"ἄνθρωπος","g":"man","s":"444","c":"noun"},{"t":"ἐκεῖνος","g":"that","s":"1565","c":"pron"},{"t":"ὅτι","g":"that","s":"3754","c":"conj"},{"t":"λήμψεταί","g":"he will receive","s":"2983","c":"verb"},{"t":"τι","g":"anything","s":"5100","c":"pron"},{"t":"παρὰ","g":"from","s":"3844","c":"prep"},{"t":"Κυρίου","g":"Lord","s":"2962","c":"noun"},{"t":"ἀνὴρ","g":"[He is] a man","s":"435","c":"noun"},{"t":"δίψυχος","g":"double-minded","s":"1374","c":"adj"},{"t":"ἀκατάστατος","g":"unstable","s":"182","c":"adj"},{"t":"ἐν","g":"in","s":"1722","c":"prep"},{"t":"πάσαις","g":"all","s":"3956","c":"adj"},{"t":"ὁδοῖς","g":"ways","s":"3598","c":"noun"},{"t":"αὐτοῦ","g":"of him","s":"846","c":"pron"}],"9":[{"t":"δὲ","g":"however","s":"1161","c":"conj"},{"t":"Καυχάσθω","g":"Let boast","s":"2744","c":"verb"},{"t":"ἀδελφὸς","g":"brother","s":"80","c":"noun"},{"t":"ταπεινὸς","g":"of low degree","s":"5011","c":"adj"},{"t":"ἐν","g":"in","s":"1722","c":"prep"},{"t":"ὕψει","g":"exaltation","s":"5311","c":"noun"},{"t":"αὐτοῦ","g":"of him","s":"846","c":"pron"},{"t":"δὲ","g":"then","s":"1161","c":"conj"},{"t":"πλούσιος","g":"rich","s":"4145","c":"adj"},{"t":"ἐν","g":"in","s":"1722","c":"prep"},{"t":"ταπεινώσει","g":"humiliation","s":"5014","c":"noun"},{"t":"αὐτοῦ","g":"of him","s":"846","c":"pron"},{"t":"ὅτι","g":"because","s":"3754","c":"conj"},{"t":"ὡς","g":"like","s":"5613","c":"conj"},{"t":"ἄνθος","g":"a flower","s":"438","c":"noun"},{"t":"χόρτου","g":"of grass","s":"5528","c":"noun"},{"t":"παρελεύσεται","g":"he will pass away","s":"3928","c":"verb"}],"11":[{"t":"γὰρ","g":"for","s":"1063","c":"conj"},{"t":"ἀνέτειλεν","g":"Has risen","s":"393","c":"verb"},{"t":"ἥλιος","g":"sun","s":"2246","c":"noun"},{"t":"σὺν","g":"with","s":"4862","c":"prep"},{"t":"καύσωνι","g":"burning heat","s":"2742","c":"noun"},{"t":"καὶ","g":"and","s":"2532","c":"conj"},{"t":"ἐξήρανεν","g":"withered","s":"3583","c":"verb"},{"t":"χόρτον","g":"grass","s":"5528","c":"noun"},{"t":"καὶ","g":"and","s":"2532","c":"conj"},{"t":"ἄνθος","g":"flower","s":"438","c":"noun"},{"t":"αὐτοῦ","g":"of it","s":"846","c":"pron"},{"t":"ἐξέπεσεν","g":"has fallen","s":"1601","c":"verb"},{"t":"καὶ","g":"and","s":"2532","c":"conj"},{"t":"εὐπρέπεια","g":"beauty","s":"2143","c":"noun"},{"t":"προσώπου","g":"appearance","s":"4383","c":"noun"},{"t":"αὐτοῦ","g":"of it","s":"846","c":"pron"},{"t":"ἀπώλετο","g":"has perished","s":"622","c":"verb"}],"12":[{"t":"Μακάριος","g":"Blessed [is the]","s":"3107","c":"adj"},{"t":"ἀνὴρ","g":"man","s":"435","c":"noun"},{"t":"ὃς","g":"who","s":"3739","c":"pron"},{"t":"ὑπομένει","g":"endures","s":"5278","c":"verb"},{"t":"πειρασμόν","g":"trial","s":"3986","c":"noun"},{"t":"ὅτι","g":"because","s":"3754","c":"conj"},{"t":"δόκιμος","g":"approved","s":"1384","c":"adj"},{"t":"γενόμενος","g":"having been","s":"1096","c":"verb"},{"t":"λήμψεται","g":"he will receive","s":"2983","c":"verb"},{"t":"στέφανον","g":"crown","s":"4735","c":"noun"},{"t":"ζωῆς","g":"of life","s":"2222","c":"noun"},{"t":"ὃν","g":"that","s":"3739","c":"pron"},{"t":"ἐπηγγείλατο","g":"He has promised","s":"1861","c":"verb"},{"t":"ἀγαπῶσιν","g":"loving","s":"25","c":"verb"},{"t":"αὐτόν","g":"Him","s":"846","c":"pron"}],"13":[{"t":"Μηδεὶς","g":"No one","s":"3367","c":"adj"},{"t":"πειραζόμενος","g":"being tempted","s":"3985","c":"verb"},{"t":"λεγέτω","g":"let say","s":"3004","c":"verb"},{"t":"Ἀπὸ","g":"By","s":"575","c":"prep"},{"t":"Θεοῦ","g":"God","s":"2316","c":"noun"},{"t":"πειράζομαι","g":"I am being tempted","s":"3985","c":"verb"}],"14":[{"t":"δὲ","g":"however","s":"1161","c":"conj"},{"t":"ἕκαστος","g":"A man","s":"1538","c":"adj"},{"t":"πειράζεται","g":"is tempted","s":"3985","c":"verb"},{"t":"ὑπὸ","g":"by","s":"5259","c":"prep"},{"t":"ἰδίας","g":"own","s":"2398","c":"adj"},{"t":"ἐπιθυμίας","g":"desire","s":"1939","c":"noun"},{"t":"ἐξελκόμενος","g":"being drawn away","s":"1828","c":"verb"},{"t":"καὶ","g":"and","s":"2532","c":"conj"},{"t":"δελεαζόμενος","g":"being enticed","s":"1185","c":"verb"}],"15":[{"t":"εἶτα","g":"Then","s":"1534","c":"adv"},{"t":"ἐπιθυμία","g":"desire","s":"1939","c":"noun"},{"t":"συλλαβοῦσα","g":"having conceived","s":"4815","c":"verb"},{"t":"τίκτει","g":"gives birth to","s":"5088","c":"verb"},{"t":"ἁμαρτίαν","g":"sin","s":"266","c":"noun"},{"t":"δὲ","g":"and","s":"1161","c":"conj"},{"t":"ἁμαρτία","g":"sin","s":"266","c":"noun"},{"t":"ἀποτελεσθεῖσα","g":"having become fully grown","s":"658","c":"verb"},{"t":"ἀποκύει","g":"brings forth","s":"616","c":"verb"},{"t":"θάνατον","g":"death","s":"2288","c":"noun"}],"16":[{"t":"Μὴ","g":"Not","s":"3361","c":"adv"},{"t":"πλανᾶσθε","g":"be misled","s":"4105","c":"verb"},{"t":"ἀδελφοί","g":"brothers","s":"80","c":"noun"},{"t":"μου","g":"my","s":"1473","c":"pron"},{"t":"ἀγαπητοί","g":"beloved","s":"27","c":"adj"}],"17":[{"t":"πᾶσα","g":"Every","s":"3956","c":"adj"},{"t":"δόσις","g":"act of giving","s":"1394","c":"noun"},{"t":"ἀγαθὴ","g":"good","s":"18","c":"adj"},{"t":"καὶ","g":"and","s":"2532","c":"conj"},{"t":"πᾶν","g":"every","s":"3956","c":"adj"},{"t":"δώρημα","g":"gift","s":"1434","c":"noun"},{"t":"τέλειον","g":"perfect","s":"5046","c":"adj"},{"t":"ἄνωθέν","g":"from above","s":"509","c":"adv"},{"t":"ἐστιν","g":"is","s":"1510","c":"verb"},{"t":"καταβαῖνον","g":"coming down","s":"2597","c":"verb"},{"t":"ἀπὸ","g":"from","s":"575","c":"prep"},{"t":"Πατρὸς","g":"Father","s":"3962","c":"noun"},{"t":"φώτων","g":"of lights","s":"5457","c":"noun"},{"t":"παρ’","g":"with","s":"3844","c":"prep"},{"t":"ᾧ","g":"whom","s":"3739","c":"pron"},{"t":"οὐκ","g":"not","s":"3756","c":"adv"},{"t":"ἔνι","g":"there is","s":"1762","c":"verb"},{"t":"παραλλαγὴ","g":"variation","s":"3883","c":"noun"},{"t":"ἢ","g":"or","s":"2228","c":"conj"},{"t":"τροπῆς","g":"of shifting","s":"5157","c":"noun"},{"t":"ἀποσκίασμα","g":"shadow","s":"644","c":"noun"}],"18":[{"t":"βουληθεὶς","g":"Having willed [it]","s":"1014","c":"verb"},{"t":"ἀπεκύησεν","g":"He brought forth","s":"616","c":"verb"},{"t":"ἡμᾶς","g":"us","s":"1473","c":"pron"},{"t":"λόγῳ","g":"by [the] word","s":"3056","c":"noun"},{"t":"ἀληθείας","g":"of truth","s":"225","c":"noun"},{"t":"εἰς","g":"for","s":"1519","c":"prep"},{"t":"εἶναι","g":"to be","s":"1510","c":"verb"},{"t":"ἡμᾶς","g":"us","s":"1473","c":"pron"},{"t":"ἀπαρχήν","g":"firstfruits","s":"536","c":"noun"},{"t":"τινα","g":"a certain","s":"5100","c":"pron"},{"t":"αὐτοῦ","g":"of His","s":"846","c":"pron"},{"t":"κτισμάτων","g":"creatures","s":"2938","c":"noun"}],"19":[{"t":"Ἴστε","g":"Know [this]","s":"1492","c":"verb"},{"t":"ἀδελφοί","g":"brothers","s":"80","c":"noun"},{"t":"μου","g":"my","s":"1473","c":"pron"},{"t":"ἀγαπητοί","g":"beloved","s":"27","c":"adj"}],"20":[{"t":"γὰρ","g":"for","s":"1063","c":"conj"},{"t":"ὀργὴ","g":"[the] anger","s":"3709","c":"noun"},{"t":"ἀνδρὸς","g":"of man","s":"435","c":"noun"},{"t":"δικαιοσύνην","g":"[the] righteousness","s":"1343","c":"noun"},{"t":"Θεοῦ","g":"of God","s":"2316","c":"noun"},{"t":"οὐκ","g":"not","s":"3756","c":"adv"},{"t":"ἐργάζεται","g":"produces","s":"2038","c":"verb"}],"21":[{"t":"διὸ","g":"Therefore","s":"1352","c":"conj"},{"t":"ἀποθέμενοι","g":"having put aside","s":"659","c":"verb"},{"t":"πᾶσαν","g":"all","s":"3956","c":"adj"},{"t":"ῥυπαρίαν","g":"filthiness","s":"4507","c":"noun"},{"t":"καὶ","g":"and","s":"2532","c":"conj"},{"t":"περισσείαν","g":"abounding","s":"4050","c":"noun"},{"t":"κακίας","g":"of wickedness","s":"2549","c":"noun"},{"t":"ἐν","g":"in","s":"1722","c":"prep"},{"t":"πραΰτητι","g":"humility","s":"4240","c":"noun"},{"t":"δέξασθε","g":"receive","s":"1209","c":"verb"},{"t":"ἔμφυτον","g":"implanted","s":"1721","c":"adj"},{"t":"λόγον","g":"word","s":"3056","c":"noun"},{"t":"δυνάμενον","g":"being able","s":"1410","c":"verb"},{"t":"σῶσαι","g":"to save","s":"4982","c":"verb"},{"t":"ψυχὰς","g":"souls","s":"5590","c":"noun"},{"t":"ὑμῶν","g":"of you","s":"4771","c":"pron"}],"22":[{"t":"δὲ","g":"however","s":"1161","c":"conj"},{"t":"γίνεσθε","g":"Be","s":"1096","c":"verb"},{"t":"ποιηταὶ","g":"doers","s":"4163","c":"noun"},{"t":"λόγου","g":"of [the] word","s":"3056","c":"noun"},{"t":"καὶ","g":"and","s":"2532","c":"conj"},{"t":"μὴ","g":"not","s":"3361","c":"adv"},{"t":"ἀκροαταὶ","g":"hearers","s":"202","c":"noun"},{"t":"μόνον","g":"only","s":"3440","c":"noun"},{"t":"παραλογιζόμενοι","g":"deceiving","s":"3884","c":"verb"},{"t":"ἑαυτούς","g":"yourselves","s":"1438","c":"pron"},{"t":"ὅτι","g":"because","s":"3754","c":"conj"},{"t":"εἴ","g":"if","s":"1487","c":"conj"},{"t":"τις","g":"anyone","s":"5100","c":"pron"},{"t":"ἀκροατὴς","g":"a hearer","s":"202","c":"noun"},{"t":"λόγου","g":"of [the] word","s":"3056","c":"noun"},{"t":"ἐστὶν","g":"is","s":"1510","c":"verb"},{"t":"καὶ","g":"and","s":"2532","c":"conj"},{"t":"οὐ","g":"not","s":"3756","c":"adv"},{"t":"ποιητής","g":"a doer","s":"4163","c":"noun"},{"t":"οὗτος","g":"this one","s":"3778","c":"pron"},{"t":"ἔοικεν","g":"is like","s":"1503","c":"verb"},{"t":"ἀνδρὶ","g":"a man","s":"435","c":"noun"},{"t":"κατανοοῦντι","g":"looking","s":"2657","c":"verb"},{"t":"πρόσωπον","g":"[the] face","s":"4383","c":"noun"},{"t":"γενέσεως","g":"natural","s":"1078","c":"noun"},{"t":"αὐτοῦ","g":"of him","s":"846","c":"pron"},{"t":"ἐν","g":"in","s":"1722","c":"prep"},{"t":"ἐσόπτρῳ","g":"a mirror","s":"2072","c":"noun"},{"t":"γὰρ","g":"for","s":"1063","c":"conj"},{"t":"κατενόησεν","g":"he has viewed","s":"2657","c":"verb"},{"t":"ἑαυτὸν","g":"himself","s":"1438","c":"pron"},{"t":"καὶ","g":"and","s":"2532","c":"conj"},{"t":"ἀπελήλυθεν","g":"has gone away","s":"565","c":"verb"},{"t":"καὶ","g":"and","s":"2532","c":"conj"},{"t":"εὐθέως","g":"immediately","s":"2112","c":"adv"},{"t":"ἐπελάθετο","g":"he has forgotten","s":"1950","c":"verb"},{"t":"ὁποῖος","g":"what like","s":"3697","c":"adj"},{"t":"ἦν","g":"he was","s":"1510","c":"verb"}],"25":[{"t":"δὲ","g":"however","s":"1161","c":"conj"},{"t":"παρακύψας","g":"having looked intently","s":"3879","c":"verb"},{"t":"εἰς","g":"into","s":"1519","c":"prep"},{"t":"νόμον","g":"[the] law","s":"3551","c":"noun"},{"t":"τέλειον","g":"perfect","s":"5046","c":"adj"},{"t":"ἐλευθερίας","g":"of freedom","s":"1657","c":"noun"},{"t":"καὶ","g":"and","s":"2532","c":"conj"},{"t":"παραμείνας","g":"having continued in [it]","s":"3887","c":"verb"},{"t":"γενόμενος","g":"having been","s":"1096","c":"verb"},{"t":"οὐκ","g":"not","s":"3756","c":"adv"},{"t":"ἀκροατὴς","g":"a hearer","s":"202","c":"noun"},{"t":"ἐπιλησμονῆς","g":"forgetful","s":"1953","c":"noun"},{"t":"ἀλλὰ","g":"but","s":"235","c":"conj"},{"t":"ποιητὴς","g":"a doer","s":"4163","c":"noun"},{"t":"ἔργου","g":"of [the] work","s":"2041","c":"noun"},{"t":"οὗτος","g":"this one","s":"3778","c":"pron"},{"t":"μακάριος","g":"blessed","s":"3107","c":"adj"},{"t":"ἐν","g":"in","s":"1722","c":"prep"},{"t":"ποιήσει","g":"work","s":"4162","c":"noun"},{"t":"αὐτοῦ","g":"of him","s":"846","c":"pron"},{"t":"ἔσται","g":"will be","s":"1510","c":"verb"}],"26":[{"t":"Εἴ","g":"If","s":"1487","c":"conj"},{"t":"τις","g":"anyone","s":"5100","c":"pron"},{"t":"δοκεῖ","g":"seems","s":"1380","c":"verb"},{"t":"θρησκὸς","g":"religious","s":"2357","c":"adj"},{"t":"εἶναι","g":"to be","s":"1510","c":"verb"},{"t":"μὴ","g":"not","s":"3361","c":"adv"},{"t":"χαλιναγωγῶν","g":"bridling","s":"5468","c":"verb"},{"t":"γλῶσσαν","g":"[the] tongue","s":"1100","c":"noun"},{"t":"ἑαυτοῦ","g":"of himself","s":"1438","c":"pron"},{"t":"ἀλλὰ","g":"but","s":"235","c":"conj"},{"t":"ἀπατῶν","g":"deceiving","s":"538","c":"verb"},{"t":"καρδίαν","g":"[the] heart","s":"2588","c":"noun"},{"t":"ἑαυτοῦ","g":"of himself","s":"1438","c":"pron"},{"t":"τούτου","g":"of this one","s":"3778","c":"pron"},{"t":"θρησκεία","g":"religion","s":"2356","c":"noun"},{"t":"μάταιος","g":"worthless [is]","s":"3152","c":"adj"}],"27":[{"t":"θρησκεία","g":"Religion","s":"2356","c":"noun"},{"t":"καθαρὰ","g":"pure","s":"2513","c":"adj"},{"t":"καὶ","g":"and","s":"2532","c":"conj"},{"t":"ἀμίαντος","g":"undefiled","s":"283","c":"adj"},{"t":"παρὰ","g":"before","s":"3844","c":"prep"},{"t":"Θεῷ","g":"God","s":"2316","c":"noun"},{"t":"καὶ","g":"and","s":"2532","c":"conj"},{"t":"Πατρὶ","g":"Father","s":"3962","c":"noun"},{"t":"ἐστίν","g":"is","s":"1510","c":"verb"},{"t":"αὕτη","g":"this","s":"3778","c":"pron"},{"t":"ἐπισκέπτεσθαι","g":"to visit","s":"1980","c":"verb"},{"t":"ὀρφανοὺς","g":"orphans","s":"3737","c":"adj"},{"t":"καὶ","g":"and","s":"2532","c":"conj"},{"t":"χήρας","g":"widows","s":"5503","c":"noun"},{"t":"ἐν","g":"in","s":"1722","c":"prep"},{"t":"θλίψει","g":"tribulation","s":"2347","c":"noun"},{"t":"αὐτῶν","g":"of them","s":"846","c":"pron"},{"t":"ἄσπιλον","g":"unstained","s":"784","c":"adj"},{"t":"ἑαυτὸν","g":"oneself","s":"1438","c":"pron"},{"t":"τηρεῖν","g":"to keep","s":"5083","c":"verb"},{"t":"ἀπὸ","g":"from","s":"575","c":"prep"},{"t":"κόσμου","g":"world","s":"2889","c":"noun"}]}